[{"url":"/weibo?q=%23%E5%A6%82%E4%BD%95%E5%91%A2%20%E5%8F%88%E8%83%BD%E6%80%8E%23","text":"еҰӮдҪ•е‘ў еҸҲиғҪжҖҺ","count":16480402,"firstSeen":"2026-03-29T07:49:43.922Z","peakCount":16480402,"prevCount":0,"velocity":100,"status":"new","textEn":"What can I do?"},{"url":"/weibo?q=%23%E4%B8%9C%E5%A4%A7%E9%AB%98%E6%AD%A6%E5%AD%A6%E9%99%A2%E9%A6%96%E6%94%AF%E6%AD%A3%E5%BC%8Fpv%E5%8F%91%E5%B8%83%23","text":"дёңеӨ§й«ҳжӯҰеӯҰйҷўйҰ–ж”ҜжӯЈејҸpvеҸ‘еёғ","count":8920864,"firstSeen":"2026-03-29T07:49:43.922Z","peakCount":8920864,"prevCount":0,"velocity":100,"status":"new"},{"url":"/weibo?q=%23%E6%9D%8E%E7%99%BD%23","text":"жқҺзҷҪ","count":426073,"firstSeen":"2026-03-29T07:49:43.922Z","peakCount":426073,"prevCount":0,"velocity":100,"status":"new"},{"url":"/weibo?q=%23%E6%AF%8F%E5%A4%A9%E5%8C%96%E5%A6%86%E7%8A%B6%E6%80%81%23","text":"жҜҸеӨ©еҢ–еҰҶзҠ¶жҖҒ","count":242939,"firstSeen":"2026-03-29T07:49:43.922Z","peakCount":242939,"prevCount":0,"velocity":100,"status":"new"},{"url":"/weibo?q=%23%E5%85%A8%E6%99%AF%E8%BF%98%E5%8E%9F%E6%A2%85%E5%A7%A8%E6%A1%88%E6%8B%90%E5%8D%96%E9%93%BE%E6%9D%A1%23","text":"е…ЁжҷҜиҝҳеҺҹжў…е§ЁжЎҲжӢҗеҚ–й“ҫжқЎ","count":224599,"firstSeen":"2026-03-29T07:49:43.922Z","peakCount":224599,"prevCount":0,"velocity":100,"status":"new"},{"url":"/weibo?q=%23%E5%8D%95%E4%BE%9D%E7%BA%AF%E6%BC%94%E5%94%B1%E4%BC%9A%E5%A5%BD%E6%83%B3%E8%B0%88%E6%81%8B%E7%88%B1%23","text":"еҚ•дҫқзәҜжј”е”ұдјҡеҘҪжғіи°ҲжҒӢзҲұ","count":212256,"firstSeen":"2026-03-29T07:49:43.922Z","peakCount":212256,"prevCount":0,"velocity":100,"status":"new"},{"url":"/weibo?q=%23%E6%B5%AA%E5%A7%907%E5%94%AF%E4%B8%80%E5%8F%8C%E9%87%91%E5%BD%B1%E5%90%8E%23","text":"жөӘе§җ7е”ҜдёҖеҸҢйҮ‘еҪұеҗҺ","count":197387,"firstSeen":"2026-03-29T07:49:43.922Z","peakCount":197387,"prevCount":0,"velocity":100,"status":"new"},{"url":"/weibo?q=%23%E6%9D%8E%E8%8D%A3%E6%B5%A9%20%E5%8D%95%E4%BE%9D%E7%BA%AF%E4%BD%A0%E6%98%AF%E6%9D%A5%E6%8A%A5%E4%BB%87%E7%9A%84%23","text":"жқҺиҚЈжө© еҚ•дҫқзәҜдҪ жҳҜжқҘжҠҘд»Үзҡ„","count":186176,"firstSeen":"2026-03-29T07:49:43.922Z","peakCount":186176,"prevCount":0,"velocity":100,"status":"new"},{"url":"/weibo?q=%23%E8%83%A1%E5%A1%9E%E4%BC%8A%E6%9C%97%E9%BB%8E%E5%B7%B4%E5%AB%A9%E5%90%8C%E6%AD%A5%E8%A2%AD%E5%87%BB%E4%BB%A5%E8%89%B2%E5%88%97%23","text":"иғЎеЎһдјҠжң—й»Һе·ҙе«©еҗҢжӯҘиўӯеҮ»д»ҘиүІеҲ—","count":163388,"firstSeen":"2026-03-29T07:49:43.922Z","peakCount":163388,"prevCount":0,"velocity":100,"status":"new"},{"url":"/weibo?q=%23%E5%A5%B9%E5%BF%98%E4%BA%86%E5%BE%88%E5%A4%9A%E5%8D%B4%E6%B2%A1%E5%BF%98%E9%80%81%E5%84%BF%E5%8F%82%E5%86%9B%E7%9A%84%E7%BA%A6%E5%AE%9A%23","text":"еҘ№еҝҳдәҶеҫҲеӨҡеҚҙжІЎеҝҳйҖҒе„ҝеҸӮеҶӣзҡ„зәҰе®ҡ","count":158223,"firstSeen":"2026-03-29T07:49:43.922Z","peakCount":158223,"prevCount":0,"velocity":100,"status":"new"},{"url":"/weibo?q=%23%E7%99%BD%E6%97%A5%E6%8F%90%E7%81%AF%E7%88%86%E5%89%A7%23","text":"зҷҪж—ҘжҸҗзҒҜзҲҶеү§","count":157521,"firstSeen":"2026-03-29T07:49:43.922Z","peakCount":157521,"prevCount":0,"velocity":100,"status":"new","textEn":"Drama during the day with a lantern"},{"url":"/weibo?q=%23%E4%B8%96%E7%95%8C%E6%9C%80%E5%A4%A7%E7%9B%B4%E5%BE%84%E9%AB%98%E9%93%81%E7%9B%BE%E6%9E%84%E6%9C%BA%E4%B8%8A%E5%B2%B8%23","text":"дё–з•ҢжңҖеӨ§зӣҙеҫ„й«ҳй“Ғзӣҫжһ„жңәдёҠеІё","count":157057,"firstSeen":"2026-03-29T07:49:43.922Z","peakCount":157057,"prevCount":0,"velocity":100,"status":"new"},{"url":"/weibo?q=%23%E5%A5%94%E8%B7%91%E5%90%A7%E6%B5%B7%E5%8F%A3%E7%9B%B4%E6%92%AD%23","text":"еҘ”и·‘еҗ§жө·еҸЈзӣҙж’ӯ","count":156589,"firstSeen":"2026-03-29T07:49:43.922Z","peakCount":156589,"prevCount":0,"velocity":100,"status":"new"},{"url":"/weibo?q=%23%E9%99%88%E7%89%A7%E9%A9%B0%E6%99%92%E8%BF%98%E9%92%B1%E6%88%AA%E5%9B%BE%23","text":"йҷҲзү§й©°жҷ’иҝҳй’ұжҲӘеӣҫ","count":155363,"firstSeen":"2026-03-29T07:49:43.922Z","peakCount":155363,"prevCount":0,"velocity":100,"status":"new"},{"url":"/weibo?q=%23%E5%BC%A0%E5%A5%95%E7%84%B6%E5%8F%82%E5%8A%A0%E8%89%BA%E8%80%83%23","text":"еј еҘ•з„¶еҸӮеҠ иүәиҖғ","count":154810,"firstSeen":"2026-03-29T07:49:43.922Z","peakCount":154810,"prevCount":0,"velocity":100,"status":"new"},{"url":"/weibo?q=%23%E5%A5%B6%E8%8C%B6%E5%BA%97%E7%82%B9%E4%B8%80%E6%9D%AF%E4%B8%8D%E5%A4%9F%E8%B5%B7%E9%80%81%23","text":"еҘ¶иҢ¶еә—зӮ№дёҖжқҜдёҚеӨҹиө·йҖҒ","count":153194,"firstSeen":"2026-03-29T07:49:43.922Z","peakCount":153194,"prevCount":0,"velocity":100,"status":"new"},{"url":"/weibo?q=%23%E5%8E%9F%E6%9D%A5%E4%BA%94%E5%93%88%E5%AF%BC%E6%BC%94%E5%B9%B6%E9%9D%9E%E4%B8%8D%E7%88%B1%E8%AF%B7%E5%A5%B3%E5%98%89%E5%AE%BE%23","text":"еҺҹжқҘдә”е“ҲеҜјжј”е№¶йқһдёҚзҲұиҜ·еҘіеҳүе®ҫ","count":152860,"firstSeen":"2026-03-29T07:49:43.922Z","peakCount":152860,"prevCount":0,"velocity":100,"status":"new"},{"url":"/weibo?q=%23%E7%BE%8E%E4%BB%A5%E8%A2%AD%E5%87%BB%E9%82%BB%E8%BF%91%E9%9C%8D%E5%B0%94%E6%9C%A8%E5%85%B9%E6%B5%B7%E5%B3%A1%E4%BC%8A%E6%9C%97%E7%A0%81%E5%A4%B4%23","text":"зҫҺд»ҘиўӯеҮ»йӮ»иҝ‘йңҚе°”жңЁе…№жө·еіЎдјҠжң—з ҒеӨҙ","count":132209,"firstSeen":"2026-03-29T07:49:43.922Z","peakCount":132209,"prevCount":0,"velocity":100,"status":"new"},{"url":"/weibo?q=%23%E5%A8%83%E5%A8%83%E8%A2%AB%E6%B5%B7%E9%B8%A5%E7%BB%91%E6%9E%B6%E4%BA%86%23","text":"еЁғеЁғиў«жө·йёҘз»‘жһ¶дәҶ","count":131696,"firstSeen":"2026-03-29T07:49:43.922Z","peakCount":131696,"prevCount":0,"velocity":100,"status":"new"},{"url":"/weibo?q=%23%E5%85%A8%E8%81%8C%E9%AB%98%E6%89%8B%E5%B7%B2%E6%B0%B8%E4%B9%85%E6%8B%89%E9%BB%91%E6%B6%89%E4%BA%8B%E7%94%BB%E5%B8%88%23","text":"е…ЁиҒҢй«ҳжүӢе·Іж°ёд№…жӢүй»‘ж¶үдәӢз”»еёҲ","count":126097,"firstSeen":"2026-03-29T07:49:43.922Z","peakCount":126097,"prevCount":0,"velocity":100,"status":"new"},{"url":"/weibo?q=%23F1%23","text":"F1","count":106907,"firstSeen":"2026-03-29T07:49:43.922Z","peakCount":106907,"prevCount":0,"velocity":100,"status":"new","textEn":"F1"},{"url":"/weibo?q=%23%E5%A4%AE%E8%A7%86%E6%9B%9D%E5%85%89%E5%85%A5%E5%AE%A4%E6%8A%A2%E5%A9%B4%E6%A1%88%E7%BB%86%E8%8A%82%23","text":"еӨ®и§Ҷжӣқе…үе…Ҙе®ӨжҠўе©ҙжЎҲз»ҶиҠӮ","count":105781,"firstSeen":"2026-03-29T07:49:43.922Z","peakCount":105781,"prevCount":0,"velocity":100,"status":"new"},{"url":"/weibo?q=%23%E6%9D%8E%E8%8D%A3%E6%B5%A9%20%E5%8D%95%E4%BE%9D%E7%BA%AF%E5%BC%BA%E8%A1%8C%E4%BE%B5%E6%9D%83%23","text":"жқҺиҚЈжө© еҚ•дҫқзәҜејәиЎҢдҫөжқғ","count":14354012,"firstSeen":"2026-03-29T06:52:57.168Z","peakCount":14354012,"prevCount":143073,"velocity":9933,"status":"rising"},{"url":"/weibo?q=%23%E6%B0%AF%E9%9B%B7%E4%BB%96%E5%AE%9A%23","text":"ж°Ҝйӣ·д»–е®ҡ","count":2212584,"firstSeen":"2026-03-29T05:51:29.308Z","peakCount":2212584,"prevCount":1153629,"velocity":92,"status":"rising"},{"url":"/weibo?q=%232026%E4%B8%AD%E5%9B%BD%E7%BD%91%E7%BB%9C%E5%AA%92%E4%BD%93%E8%AE%BA%E5%9D%9B%23","text":"2026дёӯеӣҪзҪ‘з»ңеӘ’дҪ“и®әеқӣ","count":1718782,"firstSeen":"2026-03-29T05:51:29.308Z","peakCount":1718782,"prevCount":684021,"velocity":151,"status":"rising"},{"url":"/weibo?q=%23%E6%B0%AF%E9%9B%B7%E4%BB%96%E5%AE%9A%E5%92%8C%E8%A5%BF%E6%9B%BF%E5%88%A9%E5%97%AA%E7%9A%84%E5%8C%BA%E5%88%AB%23","text":"ж°Ҝйӣ·д»–е®ҡе’ҢиҘҝжӣҝеҲ©е—Әзҡ„еҢәеҲ«","count":193086,"firstSeen":"2026-03-29T06:52:57.168Z","peakCount":193086,"prevCount":130209,"velocity":48,"status":"rising"},{"url":"/weibo?q=%23%E8%B0%A2%E5%A8%9C%E5%9C%A8%E5%BC%A0%E6%9D%B0%E6%BC%94%E5%94%B1%E4%BC%9A%E4%BA%B2%E4%BA%86%E7%A7%A6%E5%B2%9A%E6%9D%9C%E5%8D%8E%23","text":"и°ўеЁңеңЁеј жқ°жј”е”ұдјҡдәІдәҶз§ҰеІҡжқңеҚҺ","count":192548,"firstSeen":"2026-03-29T06:52:57.168Z","peakCount":192548,"prevCount":75494,"velocity":155,"status":"rising"},{"url":"/weibo?q=%23%E9%83%91%E6%99%93%E9%BE%99%E6%8B%8D%E4%BA%86%E5%A5%B3%E6%BC%94%E5%91%98%E8%A2%AB%E6%BD%9C%E8%A7%84%E5%88%99%23","text":"йғ‘жҷ“йҫҷжӢҚдәҶеҘіжј”е‘ҳиў«жҪңи§„еҲҷ","count":191654,"firstSeen":"2026-03-29T06:52:57.168Z","peakCount":191654,"prevCount":141589,"velocity":35,"status":"rising"},{"url":"/weibo?q=%23%E9%99%88%E7%89%A7%E9%A9%B0%E5%9B%9E%E5%BA%94%E4%B8%8E%E5%90%B4%E6%A5%9A%E4%B8%80%E7%9B%B8%E5%85%B3%E4%BA%89%E8%AE%AE%23","text":"йҷҲзү§й©°еӣһеә”дёҺеҗҙжҘҡдёҖзӣёе…ідәүи®®","count":157835,"firstSeen":"2026-03-29T06:52:57.168Z","peakCount":157835,"prevCount":112017,"velocity":41,"status":"rising"},{"url":"/weibo?q=%23%E6%9B%BE%E8%BE%89%E4%BA%B2%E9%9F%A9%E9%9B%A8%E5%BD%A4%E7%9A%84%E8%84%B8%23","text":"жӣҫиҫүдәІйҹ©йӣЁеҪӨзҡ„и„ё","count":153469,"firstSeen":"2026-03-29T06:52:57.168Z","peakCount":153469,"prevCount":107119,"velocity":43,"status":"rising"},{"url":"/weibo?q=%23%E6%9B%9D%E5%A5%B3%E9%A1%B6%E6%B5%81%E8%A2%AB%E5%85%AC%E5%8F%B8%E7%B4%A2%E8%B5%943%E4%BA%BF%E8%A7%A3%E7%BA%A6%E8%B4%B9%23","text":"жӣқеҘійЎ¶жөҒиў«е…¬еҸёзҙўиө”3дәҝи§ЈзәҰиҙ№","count":131630,"textEn":"It is revealed that a top female star was claimed by her company for a termination fee of NT$300 million","firstSeen":"2026-03-29T04:09:57.126Z","peakCount":147750,"prevCount":103285,"velocity":27,"status":"rising"},{"url":"/weibo?q=%23%E5%88%98%E6%B6%9B%E9%83%9D%E8%95%BE%E8%AF%B4%E7%9A%84%E6%98%AF%E8%B0%81%23","text":"еҲҳж¶ӣйғқи•ҫиҜҙзҡ„жҳҜи°Ғ","count":113510,"firstSeen":"2026-03-29T06:52:57.168Z","peakCount":113510,"prevCount":80546,"velocity":41,"status":"rising"},{"url":"/weibo?q=%23%E5%8A%A8%E6%A3%AE%20%E4%BA%BA%E6%A3%AE%23","text":"еҠЁжЈ® дәәжЈ®","count":113189,"firstSeen":"2026-03-29T06:52:57.168Z","peakCount":113189,"prevCount":68781,"velocity":65,"status":"rising"},{"url":"/weibo?q=%23%E9%98%BF%E9%82%A3%E4%BA%9A%E6%B5%B7%E5%B8%82%E8%9C%83%E6%A5%BC%23","text":"йҳҝйӮЈдәҡжө·еёӮиңғжҘј","count":292247,"textEn":"Aranya mirage","firstSeen":"2026-03-29T06:52:57.168Z","peakCount":292247,"prevCount":279598,"velocity":5,"status":"hot"},{"url":"/weibo?q=%23%E6%97%A5%E6%9C%AC%E6%8A%97%E8%AE%AE%E8%80%85%E9%AB%98%E5%96%8A%E4%B8%AD%E5%9B%BD%E5%AF%B9%E4%B8%8D%E8%B5%B7%23","text":"ж—Ҙжң¬жҠ—и®®иҖ…й«ҳе–ҠдёӯеӣҪеҜ№дёҚиө·","count":243547,"textEn":"Japanese protesters shout China is sorry","firstSeen":"2026-03-29T05:51:29.308Z","peakCount":785552,"prevCount":274448,"velocity":-11,"status":"hot"},{"url":"/weibo?q=%23%E6%97%A5%E6%9C%AC%E4%BA%BA%E5%BC%BA%E9%97%AF%E6%88%91%E4%BD%BF%E9%A6%86%E4%BA%8B%E4%BB%B6%E6%9C%80%E6%96%B0%E8%BF%9B%E5%B1%95%23","text":"ж—Ҙжң¬дәәејәй—ҜжҲ‘дҪҝйҰҶдәӢд»¶жңҖж–°иҝӣеұ•","count":187991,"firstSeen":"2026-03-29T06:52:57.168Z","peakCount":227078,"prevCount":227078,"velocity":-17,"status":"hot"},{"url":"/weibo?q=%23%E9%95%BF%E6%9C%9F%E4%B8%8D%E5%90%83%E4%B8%BB%E9%A3%9F%E8%BA%AB%E4%BD%93%E7%9A%848%E4%B8%AA%E5%8F%98%E5%8C%96%23","text":"й•ҝжңҹдёҚеҗғдё»йЈҹиә«дҪ“зҡ„8дёӘеҸҳеҢ–","count":158471,"firstSeen":"2026-03-29T04:09:57.126Z","peakCount":175812,"prevCount":131952,"velocity":20,"status":"hot"},{"url":"/weibo?q=%23%E7%BE%8E%E5%9B%BD%E5%85%A8%E5%9B%BD%E7%88%86%E5%8F%91%E5%8F%8D%E5%AF%B9%E7%89%B9%E6%9C%97%E6%99%AE%E6%94%BF%E5%BA%9C%E9%9B%86%E4%BC%9A%23","text":"зҫҺеӣҪе…ЁеӣҪзҲҶеҸ‘еҸҚеҜ№зү№жң—жҷ®ж”ҝеәңйӣҶдјҡ","count":155555,"textEn":"Rallies against Trump administration erupt across U.S.","firstSeen":"2026-03-29T04:09:57.126Z","peakCount":1132479,"prevCount":191575,"velocity":-19,"status":"hot"},{"url":"/weibo?q=%23%E4%B8%8D%E6%98%AF%E6%AD%A3%E5%89%A7%E5%B0%B1%E4%B8%8D%E7%94%A8%E8%BE%83%E7%9C%9F%E7%B2%89%E5%BA%95%E6%B6%B2%E5%B0%86%E5%86%9B%E5%90%97%23","text":"дёҚжҳҜжӯЈеү§е°ұдёҚз”ЁиҫғзңҹзІүеә•ж¶Іе°ҶеҶӣеҗ—","count":154583,"firstSeen":"2026-03-29T05:51:29.308Z","peakCount":179690,"prevCount":179690,"velocity":-14,"status":"hot"},{"url":"/weibo?q=%23%E9%80%90%E7%8E%89%20%E5%BA%86%E5%8A%9F%E5%AE%B4%23","text":"йҖҗзҺү еәҶеҠҹе®ҙ","count":152521,"firstSeen":"2026-03-29T04:09:57.126Z","peakCount":176539,"prevCount":131156,"velocity":16,"status":"hot"},{"url":"/weibo?q=%23%E5%A4%AB%E5%A6%BB%E6%88%BF%E4%BA%A7%E7%95%99%E7%BB%99%E9%95%BF%E5%AD%90%E9%95%BF%E5%AD%99%E9%81%AD%E4%B8%A4%E5%A5%B3%E5%84%BF%E5%8F%8D%E5%AF%B9%23","text":"еӨ«еҰ»жҲҝдә§з•ҷз»ҷй•ҝеӯҗй•ҝеӯҷйҒӯдёӨеҘіе„ҝеҸҚеҜ№","count":146092,"firstSeen":"2026-03-29T05:51:29.308Z","peakCount":306807,"prevCount":135668,"velocity":8,"status":"hot"},{"url":"/weibo?q=%23%E6%89%8D%E5%8F%91%E7%8E%B0%E7%8E%8B%E4%B8%80%E5%8D%9A%E4%B8%8A%E7%9A%84%E5%85%A8%E8%8B%B1%E8%AF%BE%23","text":"жүҚеҸ‘зҺ°зҺӢдёҖеҚҡдёҠзҡ„е…ЁиӢұиҜҫ","count":143313,"textEn":"Only then did I discover that Wang Yibo was taking an all-English class","firstSeen":"2026-03-29T05:51:29.308Z","peakCount":143313,"prevCount":131333,"velocity":9,"status":"hot"},{"url":"/weibo?q=%23%E5%A5%94%E8%B7%91%E5%90%A7%23","text":"еҘ”и·‘еҗ§","count":139828,"firstSeen":"2026-03-29T06:52:57.168Z","peakCount":139828,"prevCount":133117,"velocity":5,"status":"hot"},{"url":"/weibo?q=%23%E5%85%A8%E7%BA%A2%E5%A9%B519%E5%B2%81%E5%8F%91%E6%96%87%23","text":"е…Ёзәўе©ө19еІҒеҸ‘ж–Ү","count":131640,"firstSeen":"2026-03-29T06:52:57.168Z","peakCount":150360,"prevCount":150360,"velocity":-12,"status":"hot"},{"url":"/weibo?q=%23%E6%9E%97%E5%AD%90%E7%83%A8%E5%83%8F%E5%BC%A0%E5%87%8C%E8%B5%AB%E7%94%9F%E7%9A%84%23","text":"жһ—еӯҗзғЁеғҸеј еҮҢиө«з”ҹзҡ„","count":126441,"textEn":"Lin Ziye looks like Zhang Linghe","firstSeen":"2026-03-29T05:51:29.308Z","peakCount":143106,"prevCount":134018,"velocity":-6,"status":"hot"},{"url":"/weibo?q=%23QQ%E9%9F%B3%E4%B9%90%20%E8%99%9E%E4%B9%A6%E6%AC%A3%23","text":"QQйҹід№җ иҷһд№Ұж¬Ј","count":126043,"firstSeen":"2026-03-29T05:51:29.308Z","peakCount":130546,"prevCount":106528,"velocity":18,"status":"hot"},{"url":"/weibo?q=%23%E5%A5%B3%E5%AD%90%E5%8D%8A%E5%B9%B4%E6%B2%A1%E5%9B%9E%E5%AE%B6%E5%8D%A7%E5%AE%A4%E5%BC%80%E7%AA%97%E5%8F%98%E9%82%BB%E5%B1%85%E9%98%B3%E5%8F%B0%23","text":"еҘіеӯҗеҚҠе№ҙжІЎеӣһе®¶еҚ§е®ӨејҖзӘ—еҸҳйӮ»еұ…йҳіеҸ°","count":113131,"firstSeen":"2026-03-28T23:49:57.267Z","peakCount":1262296,"prevCount":104151,"velocity":9,"status":"hot"},{"url":"/weibo?q=%23%E5%BC%A0%E9%9C%87%E5%B2%B3%E6%94%B6%E8%97%8F%E5%90%90%E6%A7%BD%E5%91%A8%E6%9D%B0%E4%BC%A6%E7%9A%84%E6%96%87%E7%AB%A0%23","text":"еј йңҮеІіж”¶и—Ҹеҗҗж§Ҫе‘Ёжқ°дјҰзҡ„ж–Үз« ","count":113124,"textEn":"Zhang Chenyue collects articles complaining about Jay Chou","firstSeen":"2026-03-29T05:51:29.308Z","peakCount":126989,"prevCount":102831,"velocity":10,"status":"hot"},{"url":"/weibo?q=%23%E5%A5%88%E9%9B%AA%E7%9A%84%E8%8C%B6%E6%B2%A1%E4%BA%BA%E5%96%9D%E4%BA%86%23","text":"еҘҲйӣӘзҡ„иҢ¶жІЎдәәе–қдәҶ","count":431819,"textEn":"No one drinks NayukiвҖҷs tea anymore","firstSeen":"2026-03-29T05:51:29.308Z","peakCount":823694,"prevCount":823694,"velocity":-48,"status":"falling"},{"url":"/weibo?q=%23%E5%BE%B7%E5%9B%BD%E7%89%88%E5%B0%84%E9%9B%95%E9%A2%84%E5%91%8A%E5%A5%BD%E7%87%83%E5%A5%BD%E9%9C%87%E6%92%BC%23","text":"еҫ·еӣҪзүҲе°„йӣ•йў„е‘ҠеҘҪзҮғеҘҪйңҮж’ј","count":153960,"firstSeen":"2026-03-29T05:51:29.308Z","peakCount":262610,"prevCount":262610,"velocity":-41,"status":"falling"},{"url":"/weibo?q=%23%E8%A7%82%E4%BC%97%E5%8F%8D%E6%84%9F%E7%9A%84%E4%BB%8E%E6%9D%A5%E4%B8%8D%E6%98%AF%E5%B8%85%E5%B0%86%E5%86%9B%23","text":"и§Ӯдј—еҸҚж„ҹзҡ„д»ҺжқҘдёҚжҳҜеё…е°ҶеҶӣ","count":881123,"firstSeen":"2026-03-29T01:05:59.206Z","peakCount":881123,"prevCount":881123,"velocity":-100,"status":"gone","textEn":"ItвҖҷs never the handsome general that the audience dislikes"},{"url":"/weibo?q=%23%E6%B6%88%E6%AF%92%23","text":"ж¶ҲжҜ’","count":750058,"textEn":"disinfect","firstSeen":"2026-03-28T17:25:44.353Z","peakCount":1592883,"prevCount":750058,"velocity":-100,"status":"gone"},{"url":"/weibo?q=%23%E6%94%BF%E4%BC%81%E6%96%B0%E5%AA%92%E4%BD%93%E6%80%8E%E4%B9%88%E7%81%AB%E5%87%BA%E5%9C%88%23","text":"ж”ҝдјҒж–°еӘ’дҪ“жҖҺд№ҲзҒ«еҮәеңҲ","count":716748,"textEn":"How do new media in government and enterprises become popular?","firstSeen":"2026-03-28T21:48:58.037Z","peakCount":716748,"prevCount":716748,"velocity":-100,"status":"gone"},{"url":"/weibo?q=%23%E5%8E%9F%E6%9D%A5%E4%BD%A0%E6%98%AF%E8%BF%99%E6%A0%B7%E7%9A%84%E6%B2%B3%E5%8D%97%23","text":"еҺҹжқҘдҪ жҳҜиҝҷж ·зҡ„жІіеҚ—","count":667001,"firstSeen":"2026-03-28T16:16:15.074Z","peakCount":667001,"prevCount":667001,"velocity":-100,"status":"gone","textEn":"It turns out you are like this in Henan"},{"url":"/weibo?q=%23%E5%A4%AA%E5%8E%9F%E7%81%AB%E7%81%BE%E8%BF%91%E8%B7%9D%E7%A6%BB%E7%9B%AE%E5%87%BB%E8%80%85%E7%9B%B4%E5%91%BC%E5%A5%BD%E5%AE%B3%E6%80%95%23","text":"еӨӘеҺҹзҒ«зҒҫиҝ‘и·қзҰ»зӣ®еҮ»иҖ…зӣҙе‘јеҘҪе®іжҖ•","count":654299,"textEn":"Eyewitnesses of the Taiyuan fire at close range said they were so scared","firstSeen":"2026-03-28T16:16:15.074Z","peakCount":931032,"prevCount":654299,"velocity":-100,"status":"gone"},{"url":"/weibo?q=%23%E5%A4%A7%E5%9B%BD%E9%87%8D%E5%99%A8%E5%AF%86%E9%9B%86%E4%B8%8A%E6%96%B0%E6%83%8A%E5%96%9C%E4%B8%8D%E6%96%AD%23","text":"еӨ§еӣҪйҮҚеҷЁеҜҶйӣҶдёҠж–°жғҠе–ңдёҚж–ӯ","count":634718,"firstSeen":"2026-03-29T04:09:57.126Z","peakCount":634718,"prevCount":634718,"velocity":-100,"status":"gone"},{"url":"/weibo?q=%23%E5%A4%AA%E5%8E%9F%E7%81%AB%E7%81%BE%E5%B7%B2%E8%87%B41%E6%AD%BB25%E4%BC%A4%23","text":"еӨӘеҺҹзҒ«зҒҫе·ІиҮҙ1жӯ»25дјӨ","count":362199,"firstSeen":"2026-03-28T16:16:15.074Z","peakCount":612516,"prevCount":362199,"velocity":-100,"status":"gone","textEn":"Taiyuan fire kills 1 and injures 25"},{"url":"/weibo?q=%23%E5%A4%AA%E5%8E%9F%E7%81%AB%E7%81%BE%23","text":"еӨӘеҺҹзҒ«зҒҫ","count":288088,"textEn":"Taiyuan fire","firstSeen":"2026-03-28T16:16:15.074Z","peakCount":628171,"prevCount":288088,"velocity":-100,"status":"gone"},{"url":"/weibo?q=%23%E5%A5%B3%E5%AD%90%E8%A2%AB%E7%BE%81%E6%8A%BC821%E5%A4%A9%E6%97%A0%E7%BD%AA%E9%87%8A%E6%94%BE%E5%9B%BD%E8%B5%94%E8%A2%AB%E5%8F%AB%E5%81%9C%23","text":"еҘіеӯҗиў«зҫҒжҠј821еӨ©ж— зҪӘйҮҠж”ҫеӣҪиө”иў«еҸ«еҒң","count":261139,"textEn":"The woman was released without charge after 821 days in custody and the state compensation was suspended.","firstSeen":"2026-03-28T23:49:57.267Z","peakCount":709460,"prevCount":261139,"velocity":-100,"status":"gone"},{"url":"/weibo?q=%23%E6%B0%A6%E6%B0%94%E4%BB%B7%E6%A0%BC%E6%9A%B4%E6%B6%A850%25%23","text":"ж°Ұж°”д»·ж јжҡҙж¶Ё50%","count":249106,"textEn":"Helium prices skyrocketed by 50%","firstSeen":"2026-03-28T16:16:15.074Z","peakCount":580213,"prevCount":249106,"velocity":-100,"status":"gone"},{"url":"/weibo?q=%23%E5%BC%A0%E5%87%8C%E8%B5%AB%E7%B4%A0%E9%A2%9C%E9%A1%BA%E6%AF%9B%E8%B7%AF%E9%80%8F%23","text":"еј еҮҢиө«зҙ йўңйЎәжҜӣи·ҜйҖҸ","count":213583,"firstSeen":"2026-03-29T04:09:57.126Z","peakCount":213583,"prevCount":213583,"velocity":-100,"status":"gone"},{"url":"/weibo?q=%23%E4%B8%96%E4%B8%8A%E9%A1%B6%E5%A5%BD%E9%A1%B6%E5%A5%BD%E7%9A%84%E8%80%81%E5%A4%AA%E5%A9%86%E8%B5%B0%E4%BA%86%23","text":"дё–дёҠйЎ¶еҘҪйЎ¶еҘҪзҡ„иҖҒеӨӘе©Ҷиө°дәҶ","count":204482,"textEn":"The best old woman in the world is gone","firstSeen":"2026-03-28T17:55:10.453Z","peakCount":976902,"prevCount":204482,"velocity":-100,"status":"gone"},{"url":"/weibo?q=%23%E6%9D%A8%E7%B4%AB%E7%BB%99%E9%BB%84%E7%81%BF%E7%81%BF%E7%9A%84%E6%B5%AA%E5%A7%90%E5%BB%BA%E8%AE%AE%23","text":"жқЁзҙ«з»ҷй»„зҒҝзҒҝзҡ„жөӘе§җе»әи®®","count":194262,"firstSeen":"2026-03-28T23:49:57.267Z","peakCount":194262,"prevCount":194262,"velocity":-100,"status":"gone","textEn":"Yang Zi gives advice to Huang CancanвҖҷs sister Lang"},{"url":"/weibo?q=%23%E7%BE%8E%E5%86%9B%E7%A6%8F%E7%89%B9%E5%8F%B7%E8%88%AA%E6%AF%8D%E6%8A%B5%E6%B8%AF%E5%85%8B%E7%BD%97%E5%9C%B0%E4%BA%9A%E7%BB%B4%E4%BF%AE%23","text":"зҫҺеҶӣзҰҸзү№еҸ·иҲӘжҜҚжҠөжёҜе…ӢзҪ—ең°дәҡз»ҙдҝ®","count":192110,"firstSeen":"2026-03-29T01:05:59.206Z","peakCount":192110,"prevCount":192110,"velocity":-100,"status":"gone"},{"url":"/weibo?q=%23%E6%B7%B1%E5%A4%9C%E9%81%87%E5%93%AD%E6%B3%A3%E5%A5%B3%E5%AD%90%E5%B8%A6%E5%85%B6%E5%9B%9E%E5%AE%B6%E9%81%AD%E4%BB%99%E4%BA%BA%E8%B7%B3%23","text":"ж·ұеӨңйҒҮе“ӯжіЈеҘіеӯҗеёҰе…¶еӣһе®¶йҒӯд»ҷдәәи·і","count":184915,"firstSeen":"2026-03-29T04:09:57.126Z","peakCount":184915,"prevCount":184915,"velocity":-100,"status":"gone"},{"url":"/weibo?q=%23%E4%B8%A5%E5%B1%B9%E5%AE%BD%E5%9B%9E%E5%BA%94%E6%B3%95%E6%8B%89%E5%88%A9%E9%81%87%E6%B3%95%E6%8B%89%E5%88%A9%23","text":"дёҘеұ№е®Ҫеӣһеә”жі•жӢүеҲ©йҒҮжі•жӢүеҲ©","count":183330,"firstSeen":"2026-03-28T23:49:57.267Z","peakCount":183330,"prevCount":183330,"velocity":-100,"status":"gone"},{"url":"/weibo?q=%23%E4%BC%8A%E6%9C%97%E8%BF%9E%E9%81%AD%E9%87%8D%E5%88%9B%E7%BB%9D%E5%9C%B0%E5%8F%8D%E5%87%BB%23","text":"дјҠжң—иҝһйҒӯйҮҚеҲӣз»қең°еҸҚеҮ»","count":177616,"textEn":"Iran was hit hard and fought back","firstSeen":"2026-03-28T16:16:15.074Z","peakCount":636457,"prevCount":177616,"velocity":-100,"status":"gone"},{"url":"/weibo?q=%23%E5%AE%98%E6%96%B9%E9%80%9A%E6%8A%A5%E7%94%B3%E8%AF%B7%E5%9B%BD%E5%AE%B6%E8%B5%94%E5%81%BF%E8%A2%AB%E4%B8%AD%E6%AD%A2%E5%8A%9E%E7%90%86%23","text":"е®ҳж–№йҖҡжҠҘз”іиҜ·еӣҪе®¶иө”еҒҝиў«дёӯжӯўеҠһзҗҶ","count":176962,"firstSeen":"2026-03-29T01:05:59.206Z","peakCount":379875,"prevCount":176962,"velocity":-100,"status":"gone","textEn":"Official notification that application for state compensation has been suspended"},{"url":"/weibo?q=%23%E5%A4%AA%E5%8E%9F%E7%81%AB%E7%81%BE%E6%9C%80%E5%85%88%E8%B5%B7%E7%81%AB%E8%A7%86%E9%A2%91%E6%9B%9D%E5%85%89%23","text":"еӨӘеҺҹзҒ«зҒҫжңҖе…Ҳиө·зҒ«и§Ҷйў‘жӣқе…ү","count":176150,"firstSeen":"2026-03-29T04:09:57.126Z","peakCount":176150,"prevCount":176150,"velocity":-100,"status":"gone","textEn":"Video of the first fire in Taiyuan exposed"},{"url":"/weibo?q=%23%E7%BE%8E%E6%B0%91%E4%BC%97%E8%AF%B4%E5%8F%8D%E5%AF%B9%E7%BE%8E%E5%9B%BD%E6%AD%A3%E5%9C%A8%E5%8F%91%E7%94%9F%E7%9A%84%E4%BA%8B%23","text":"зҫҺж°‘дј—иҜҙеҸҚеҜ№зҫҺеӣҪжӯЈеңЁеҸ‘з”ҹзҡ„дәӢ","count":175343,"firstSeen":"2026-03-29T04:09:57.126Z","peakCount":175343,"prevCount":175343,"velocity":-100,"status":"gone"},{"url":"/weibo?q=%23%E4%BD%95%E8%80%81%E5%B8%88%E7%BB%B4%E5%98%89%E5%A5%BD%E5%85%AD%E5%93%AD%E4%BA%86%23","text":"дҪ•иҖҒеёҲз»ҙеҳүеҘҪе…ӯе“ӯдәҶ","count":174818,"textEn":"Teacher He Weijia cried for six months","firstSeen":"2026-03-29T01:05:59.206Z","peakCount":536147,"prevCount":174818,"velocity":-100,"status":"gone"},{"url":"/weibo?q=%23%E7%8C%AB%E7%9A%84%E5%81%B7%E7%AA%A5%E6%AC%B2%23","text":"зҢ«зҡ„еҒ·зӘҘж¬І","count":174619,"firstSeen":"2026-03-29T04:09:57.126Z","peakCount":174619,"prevCount":174619,"velocity":-100,"status":"gone","textEn":"Cat's voyeurism"},{"url":"/weibo?q=%23%E5%A4%AA%E5%8E%9F%E7%81%AB%E7%81%BE%E5%B7%B2%E8%87%B43%E6%AD%BB23%E4%BC%A4%23","text":"еӨӘеҺҹзҒ«зҒҫе·ІиҮҙ3жӯ»23дјӨ","count":161616,"firstSeen":"2026-03-29T01:05:59.206Z","peakCount":365996,"prevCount":161616,"velocity":-100,"status":"gone"},{"url":"/weibo?q=%23%E6%88%91%E4%B8%8D%E5%B8%8C%E6%9C%9B%E6%95%8C%E4%BA%BA%E6%8D%A1%E5%88%B0%E6%88%91%E7%9A%84%E7%94%B5%E8%A7%86%E5%B0%B1%E8%83%BD%E7%9C%8B%23","text":"жҲ‘дёҚеёҢжңӣж•ҢдәәжҚЎеҲ°жҲ‘зҡ„з”өи§Ҷе°ұиғҪзңӢ","count":161362,"textEn":"I don't want the enemy to pick up my TV and watch it","firstSeen":"2026-03-28T23:49:57.267Z","peakCount":161362,"prevCount":161362,"velocity":-100,"status":"gone"},{"url":"/weibo?q=%23%E7%BE%8E%E5%86%9B%E6%88%96%E5%87%BA%E5%8A%A8%E4%B8%8A%E5%8D%83%E4%BA%BA%E5%A4%BA%E5%8F%96%E4%BC%8A%E6%9C%97%E6%B5%93%E7%BC%A9%E9%93%80%23","text":"зҫҺеҶӣжҲ–еҮәеҠЁдёҠеҚғдәәеӨәеҸ–дјҠжң—жө“зј©й“Җ","count":160441,"firstSeen":"2026-03-29T01:05:59.206Z","peakCount":160441,"prevCount":160441,"velocity":-100,"status":"gone"},{"url":"/weibo?q=%23%E5%A4%AA%E5%8E%9F%E7%81%AB%E7%81%BE%E6%88%96%E5%9B%A0%E9%85%92%E5%BA%97%E5%A4%96%E7%AB%8B%E9%9D%A2%E8%B5%B7%E7%81%AB%E5%BC%95%E5%8F%91%23","text":"еӨӘеҺҹзҒ«зҒҫжҲ–еӣ й…’еә—еӨ–з«Ӣйқўиө·зҒ«еј•еҸ‘","count":159317,"firstSeen":"2026-03-28T16:16:15.074Z","peakCount":159317,"prevCount":159317,"velocity":-100,"status":"gone","textEn":"The Taiyuan fire may have been caused by a fire on the hotel facade"},{"url":"/weibo?q=%23%E9%BB%91%E9%BE%99%E6%B1%9F%E6%B5%B7%E6%9E%97%E4%B8%80%E6%A5%BC%E6%88%BF%E5%9D%8D%E5%A1%8C9%E4%BA%BA%E8%A2%AB%E5%9B%B0%23","text":"й»‘йҫҷжұҹжө·жһ—дёҖжҘјжҲҝеқҚеЎҢ9дәәиў«еӣ°","count":156178,"firstSeen":"2026-03-29T05:51:29.308Z","peakCount":156178,"prevCount":156178,"velocity":-100,"status":"gone"},{"url":"/weibo?q=%23%E6%89%AC%E9%A9%AC%E8%B5%9B%E9%81%93%E6%83%8A%E7%8E%B0%E6%88%8F%E7%B2%BE%E9%99%AA%E8%B7%91%E6%90%AD%E5%AD%90%23","text":"жү¬й©¬иөӣйҒ“жғҠзҺ°жҲҸзІҫйҷӘи·‘жҗӯеӯҗ","count":152950,"firstSeen":"2026-03-29T04:09:57.126Z","peakCount":152950,"prevCount":152950,"velocity":-100,"status":"gone","textEn":"A surprise showman appeared at the Yangma Raceway to accompany the runners"},{"url":"/weibo?q=%23%E4%BB%A5%E8%89%B2%E5%88%97%E4%B8%89%E9%9D%A2%E5%8F%97%E6%95%8C%23","text":"д»ҘиүІеҲ—дёүйқўеҸ—ж•Ң","count":149464,"textEn":"Israel is surrounded by enemies on three sides","firstSeen":"2026-03-28T19:48:18.338Z","peakCount":205973,"prevCount":149464,"velocity":-100,"status":"gone"},{"url":"/weibo?q=%23%E8%BF%AA%E4%B8%BD%E7%83%AD%E5%B7%B4%E6%9C%89%E9%AB%98%E5%BA%A6%E8%BF%91%E8%A7%86%23","text":"иҝӘдёҪзғӯе·ҙжңүй«ҳеәҰиҝ‘и§Ҷ","count":146938,"textEn":"Dilraba is highly myopic","firstSeen":"2026-03-28T16:16:15.074Z","peakCount":266412,"prevCount":146938,"velocity":-100,"status":"gone"},{"url":"/weibo?q=%23%E5%B8%A618%E8%A2%8B%E6%AF%92%E5%93%81%E5%85%A5%E5%A2%83%E5%8C%85%E8%A3%85%E4%B8%8A%E5%8D%B0%E5%A4%A7%E9%BA%BB%E6%A0%87%E8%AF%86%23","text":"еёҰ18иўӢжҜ’е“Ғе…ҘеўғеҢ…иЈ…дёҠеҚ°еӨ§йә»ж ҮиҜҶ","count":143613,"firstSeen":"2026-03-29T01:05:59.206Z","peakCount":143613,"prevCount":143613,"velocity":-100,"status":"gone","textEn":"Bringing 18 bags of drugs into the country with marijuana logo printed on the packaging"},{"url":"/weibo?q=%23%E7%BE%8E%E5%9B%BD1000%E4%BA%BA%E5%8C%85%E5%9B%B4%E6%94%BF%E5%BA%9C%E6%9C%BA%E6%9E%84%E5%A4%A7%E6%A5%BC%23","text":"зҫҺеӣҪ1000дәәеҢ…еӣҙж”ҝеәңжңәжһ„еӨ§жҘј","count":142538,"firstSeen":"2026-03-29T04:09:57.126Z","peakCount":827100,"prevCount":142538,"velocity":-100,"status":"gone"},{"url":"/weibo?q=%23%E6%84%9A%E5%85%AC%E7%94%9F%E7%9A%84%E6%98%AF%E4%BD%A0%E4%BF%A9%E5%B1%B1%E6%97%A9%E7%A7%BB%E8%B5%B0%E4%BA%86%23","text":"ж„ҡе…¬з”ҹзҡ„жҳҜдҪ дҝ©еұұж—©з§»иө°дәҶ","count":138298,"firstSeen":"2026-03-29T04:09:57.126Z","peakCount":138298,"prevCount":138298,"velocity":-100,"status":"gone"},{"url":"/weibo?q=%23%E6%84%9F%E8%A7%89%E5%9E%8B%E4%BA%BA%E6%A0%BC%23","text":"ж„ҹи§үеһӢдәәж ј","count":135258,"firstSeen":"2026-03-29T04:09:57.126Z","peakCount":135258,"prevCount":135258,"velocity":-100,"status":"gone"},{"url":"/weibo?q=%23%E8%A2%AB%E6%8B%90%E7%94%B7%E5%AD%90%E7%88%B1%E5%90%83%E6%8A%98%E8%80%B3%E6%A0%B9%E5%9D%9A%E4%BF%A1%E6%98%AF%E4%BA%91%E8%B4%B5%E5%B7%9D%E4%BA%BA%23","text":"иў«жӢҗз”·еӯҗзҲұеҗғжҠҳиҖіж №еқҡдҝЎжҳҜдә‘иҙөе·қдәә","count":134826,"firstSeen":"2026-03-29T01:05:59.206Z","peakCount":134826,"prevCount":134826,"velocity":-100,"status":"gone"},{"url":"/weibo?q=%2321%E5%B9%B4%E4%BA%86%E5%8F%B6%E4%B8%80%E8%8C%9C%E9%80%89%E6%AD%8C%E9%A3%8E%E6%A0%BC%E8%BF%98%E8%BF%99%E6%A0%B7%23","text":"21е№ҙдәҶеҸ¶дёҖиҢңйҖүжӯҢйЈҺж јиҝҳиҝҷж ·","count":133787,"firstSeen":"2026-03-29T05:51:29.308Z","peakCount":133787,"prevCount":133787,"velocity":-100,"status":"gone","textEn":"ItвҖҷs been 21 years and Ye YiqianвҖҷs song selection style is still the same"},{"url":"/weibo?q=%23%E5%85%B3%E4%BA%8E%E9%A6%99%E6%B8%AF%E7%9A%84%E5%86%B7%E7%9F%A5%E8%AF%86%23","text":"е…ідәҺйҰҷжёҜзҡ„еҶ·зҹҘиҜҶ","count":126934,"firstSeen":"2026-03-29T05:51:29.308Z","peakCount":126934,"prevCount":126934,"velocity":-100,"status":"gone"},{"url":"/weibo?q=%23%E7%94%B7%E5%AD%90%E4%B8%80%E6%83%B3%E6%8A%BD%E7%83%9F%E5%B0%B1%E4%B9%B0%E5%BD%A9%E7%A5%A8%E4%B8%AD%E4%BA%86701%E4%B8%87%23","text":"з”·еӯҗдёҖжғіжҠҪзғҹе°ұд№°еҪ©зҘЁдёӯдәҶ701дёҮ","count":121433,"firstSeen":"2026-03-29T04:09:57.126Z","peakCount":121433,"prevCount":121433,"velocity":-100,"status":"gone","textEn":"Man bought lottery ticket when he wanted to smoke and won 7.01 million"},{"url":"/weibo?q=%23%E9%95%BF%E7%8E%89%E8%B7%AF%E5%91%A2%E8%B7%AF%E5%91%A2%20%E8%B0%A2%E5%BE%81%E5%98%B4%E5%91%A2%E5%98%B4%E5%91%A2%23","text":"й•ҝзҺүи·Ҝе‘ўи·Ҝе‘ў и°ўеҫҒеҳҙе‘ўеҳҙе‘ў","count":120359,"firstSeen":"2026-03-29T01:05:59.206Z","peakCount":120359,"prevCount":120359,"velocity":-100,"status":"gone"},{"url":"/weibo?q=%23%E4%BD%8E%E7%B2%BE%E5%8A%9B%E4%BA%BA%E7%BE%A4%E7%9A%84%E5%91%A8%E6%9C%AB%E5%AE%89%E6%8E%92belike%23","text":"дҪҺзІҫеҠӣдәәзҫӨзҡ„е‘Ёжң«е®үжҺ’belike","count":119290,"textEn":"Weekend arrangements for people with low energy belike","firstSeen":"2026-03-28T16:16:15.074Z","peakCount":316928,"prevCount":119290,"velocity":-100,"status":"gone"},{"url":"/weibo?q=%23%E7%86%AC%E5%A4%9C%E8%87%B4%E7%98%AB%E5%A4%A7%E5%AD%A6%E7%94%9F%E5%AE%B6%E5%B1%9E%E5%8F%91%E5%A3%B0%23","text":"зҶ¬еӨңиҮҙзҳ«еӨ§еӯҰз”ҹе®¶еұһеҸ‘еЈ°","count":117156,"firstSeen":"2026-03-29T04:09:57.126Z","peakCount":117156,"prevCount":117156,"velocity":-100,"status":"gone","textEn":"The family of a college student who was paralyzed after staying up late speaks out"},{"url":"/weibo?q=%23%E7%8E%8B%E4%BF%8A%E5%87%AF%E5%9B%9E%E5%BA%94%E6%8B%BF%E9%94%99%E5%A5%96%E6%9D%AF%E4%BA%86%23","text":"зҺӢдҝҠеҮҜеӣһеә”жӢҝй”ҷеҘ–жқҜдәҶ","count":116375,"firstSeen":"2026-03-29T01:05:59.206Z","peakCount":182458,"prevCount":116375,"velocity":-100,"status":"gone"},{"url":"/weibo?q=%23%E5%A5%B3%E5%AD%90%E6%96%AD%E7%A2%B3%E6%B0%B42%E6%9C%88%E7%A1%AE%E8%AF%8A%E7%B3%96%E5%B0%BF%E7%97%85%E5%89%8D%E6%9C%9F%23","text":"еҘіеӯҗж–ӯзўіж°ҙ2жңҲзЎ®иҜҠзі–е°ҝз—…еүҚжңҹ","count":114835,"textEn":"Woman cuts carbs and is diagnosed with prediabetes in February","firstSeen":"2026-03-28T16:16:15.074Z","peakCount":675272,"prevCount":114835,"velocity":-100,"status":"gone"},{"url":"/weibo?q=%23%E7%A7%A6%E5%B2%9A%E5%9B%9E%E5%BA%94%E8%8A%B1%E5%B0%91%E4%B8%8E%E5%AE%A2%E6%A0%88%E5%93%AA%E4%B8%AA%E6%9B%B4%E5%BF%AB%E4%B9%90%23","text":"з§ҰеІҡеӣһеә”иҠұе°‘дёҺе®ўж Ҳе“ӘдёӘжӣҙеҝ«д№җ","count":114030,"firstSeen":"2026-03-29T05:51:29.308Z","peakCount":133016,"prevCount":114030,"velocity":-100,"status":"gone"},{"url":"/weibo?q=%23%E5%85%A8%E8%81%8C%E9%AB%98%E6%89%8B%E8%87%B4%E6%AD%89%23","text":"е…ЁиҒҢй«ҳжүӢиҮҙжӯү","count":111437,"firstSeen":"2026-03-29T05:51:29.308Z","peakCount":160573,"prevCount":111437,"velocity":-100,"status":"gone"},{"url":"/weibo?q=%23%E6%9D%8E%E6%98%8C%E9%92%B0%E5%86%8D%E5%A9%9A%E5%A6%BB%E5%AD%90%E5%8F%91%E6%96%87%E7%BC%85%E6%80%80%E6%9D%8E%E6%98%8C%E9%92%B0%23","text":"жқҺжҳҢй’°еҶҚе©ҡеҰ»еӯҗеҸ‘ж–Үзј…жҖҖжқҺжҳҢй’°","count":110485,"firstSeen":"2026-03-28T16:16:15.074Z","peakCount":110485,"prevCount":110485,"velocity":-100,"status":"gone","textEn":"Li ChangyuвҖҷs remarried wife posted a message in memory of Li Changyu"},{"url":"/weibo?q=%23%E7%AB%99%E5%A7%90%E6%84%9A%E4%BA%BA%E8%8A%82%E5%9B%A2%E5%BB%BA%E9%A2%84%E5%91%8A%23","text":"з«ҷе§җж„ҡдәәиҠӮеӣўе»әйў„е‘Ҡ","count":110164,"textEn":"ZhanjieвҖҷs April FoolвҖҷs Day Team Building Preview","firstSeen":"2026-03-28T16:16:15.074Z","peakCount":570470,"prevCount":110164,"velocity":-100,"status":"gone"},{"url":"/weibo?q=%23%E7%94%B7%E5%AD%90%E7%A7%81%E4%B8%8B%E9%81%97%E5%98%B1%E6%88%BF%E5%AD%90%E7%BB%99%E5%A6%B9%E5%A6%B9%E5%90%8E%E5%A6%BB%E5%AD%90%E8%B5%B7%E8%AF%89%23","text":"з”·еӯҗз§ҒдёӢйҒ—еҳұжҲҝеӯҗз»ҷеҰ№еҰ№еҗҺеҰ»еӯҗиө·иҜү","count":110016,"firstSeen":"2026-03-29T01:05:59.206Z","peakCount":110016,"prevCount":110016,"velocity":-100,"status":"gone"},{"url":"/weibo?q=%23%E5%85%A8%E7%BA%A2%E5%A9%B5%E7%A7%B0%E5%BA%8A%E4%B8%8A%E6%91%86%E6%BB%A1%E4%BA%86%E4%B9%8C%E9%BE%9F%E7%8E%A9%E5%81%B6%23","text":"е…Ёзәўе©өз§°еәҠдёҠж‘Ҷж»ЎдәҶд№ҢйҫҹзҺ©еҒ¶","count":109883,"firstSeen":"2026-03-29T04:09:57.126Z","peakCount":176862,"prevCount":109883,"velocity":-100,"status":"gone"},{"url":"/weibo?q=%23%E4%BC%8A%E6%9C%97%E6%AD%A3%E5%BC%8F%E5%9B%9E%E5%BA%94%E7%BE%8E%E5%9B%BD15%E7%82%B9%E5%81%9C%E7%81%AB%E5%8D%8F%E8%AE%AE%23","text":"дјҠжң—жӯЈејҸеӣһеә”зҫҺеӣҪ15зӮ№еҒңзҒ«еҚҸи®®","count":109204,"textEn":"Iran formally responds to US 15-point ceasefire agreement","firstSeen":"2026-03-28T16:16:15.074Z","peakCount":166695,"prevCount":109204,"velocity":-100,"status":"gone"}]