[{"url":"/weibo?q=%23%E8%B0%B7%E7%88%B1%E5%87%8CU%E5%9E%8B%E5%9C%BA%E5%9C%B0%E5%86%B3%E8%B5%9B%E6%88%96%E5%8F%96%E6%B6%88%23","text":"谷爱凌U型场地决赛或取消","count":1118957,"firstSeen":"2026-02-22T03:12:39.865Z","peakCount":1118957,"prevCount":0,"velocity":100,"status":"new","textEn":"Gu Ailing’s U-shaped field final may be cancelled"},{"url":"/weibo?q=%23%E5%A5%B3%E7%94%9F%E8%A2%AB%E5%82%AC%E5%A9%9A6%E5%B2%81%E4%BE%84%E5%AD%90%E5%B8%AE%E5%BF%99%E5%8F%8D%E5%87%BB%23","text":"女生被催婚6岁侄子帮忙反击","count":834506,"firstSeen":"2026-02-22T03:12:39.865Z","peakCount":834506,"prevCount":0,"velocity":100,"status":"new"},{"url":"/weibo?q=%23%E8%B0%A2%E6%99%AF%E8%A1%8C%E5%8E%9F%E5%9E%8B%E6%98%AF%E8%83%A1%E6%AD%8C%23","text":"谢景行原型是胡歌","count":550949,"firstSeen":"2026-02-22T03:12:39.865Z","peakCount":550949,"prevCount":0,"velocity":100,"status":"new"},{"url":"/weibo?q=%23%E6%B2%88%E5%A6%99%E5%8E%9F%E5%9E%8B%20%E7%8E%8B%E8%89%B3%23","text":"沈妙原型 王艳","count":442955,"firstSeen":"2026-02-22T03:12:39.865Z","peakCount":442955,"prevCount":0,"velocity":100,"status":"new"},{"url":"/weibo?q=%23%E7%AA%81%E7%84%B6%E6%84%8F%E8%AF%86%E5%88%B0%E7%BB%8F%E5%B8%B8%E4%B9%A0%E6%83%AF%E6%80%A7%E9%9C%B8%E5%87%8C%E8%87%AA%E5%B7%B1%23","text":"突然意识到经常习惯性霸凌自己","count":346589,"firstSeen":"2026-02-22T03:12:39.865Z","peakCount":346589,"prevCount":0,"velocity":100,"status":"new"},{"url":"/weibo?q=%23%E6%9D%A8%E6%B4%8B%E5%91%A8%E6%B4%81%E7%90%BC%E4%B8%8D%E8%AE%A9%E6%B1%9F%E5%B1%B1%E5%BC%80%E6%9C%BA%E5%90%8C%E6%A1%86%23","text":"杨洋周洁琼不让江山开机同框","count":338679,"firstSeen":"2026-02-22T03:12:39.865Z","peakCount":338679,"prevCount":0,"velocity":100,"status":"new"},{"url":"/weibo?q=%2375%E5%B2%81%E9%92%93%E5%B8%9D%E9%BB%91%E5%A4%A7%E7%88%B7%E5%8E%BB%E4%B8%96%23","text":"75岁钓帝黑大爷去世","count":292434,"firstSeen":"2026-02-22T03:12:39.865Z","peakCount":292434,"prevCount":0,"velocity":100,"status":"new"},{"url":"/weibo?q=%23%E8%BF%99%E6%89%8D%E6%98%AF%E6%88%91%E6%83%B3%E8%A6%81%E7%9A%84%E5%B0%86%E9%97%A8%E6%AF%92%E5%90%8E%23","text":"这才是我想要的将门毒后","count":226392,"firstSeen":"2026-02-22T03:12:39.865Z","peakCount":226392,"prevCount":0,"velocity":100,"status":"new"},{"url":"/weibo?q=%23%E6%92%92%E5%A8%87%E6%97%B6%E6%B2%A1%E6%8E%A7%E5%88%B6%E5%A5%BD%E5%8A%9B%E5%BA%A6%E7%9A%84%E5%B0%8F%E7%8B%97%23","text":"撒娇时没控制好力度的小狗","count":191366,"firstSeen":"2026-02-22T03:12:39.865Z","peakCount":191366,"prevCount":0,"velocity":100,"status":"new"},{"url":"/weibo?q=%23%E8%B4%9D%E5%8A%A0%E5%B0%94%E6%B9%96%E4%BA%8B%E6%95%858%E4%BA%BA%E8%BA%AB%E4%BB%BD%E5%85%A8%E9%83%A8%E7%A1%AE%E8%AE%A4%23","text":"贝加尔湖事故8人身份全部确认","count":177339,"firstSeen":"2026-02-22T03:12:39.865Z","peakCount":177339,"prevCount":0,"velocity":100,"status":"new"},{"url":"/weibo?q=%23%E5%B1%B1%E8%A5%BF%E6%96%87%E6%97%85%E5%B1%80%E5%9B%9E%E5%BA%94%E5%87%BA%E7%A7%9F%E6%89%93%E6%8A%98%E5%8D%B4%E8%A6%81%E5%8F%B8%E6%9C%BA%E8%B4%B4%E9%92%B1%23","text":"山西文旅局回应出租打折却要司机贴钱","count":161997,"firstSeen":"2026-02-22T03:12:39.865Z","peakCount":161997,"prevCount":0,"velocity":100,"status":"new","textEn":"Shanxi Culture and Tourism Bureau responded to rental discounts but asked drivers to pay"},{"url":"/weibo?q=%23%E7%8E%8B%E9%B9%A4%E6%A3%A3%E5%AE%8B%E8%8C%9C%E6%81%B3%E6%B1%82%E8%A7%82%E4%BC%97%E5%A4%9A%E7%BB%99%E4%B8%80%E4%BA%9B%E6%9C%BA%E4%BC%9A%23","text":"王鹤棣宋茜恳求观众多给一些机会","count":159832,"firstSeen":"2026-02-22T03:12:39.865Z","peakCount":159832,"prevCount":0,"velocity":100,"status":"new"},{"url":"/weibo?q=%23%E6%9D%8E%E6%98%80%E9%94%90%E5%BD%93%E4%B8%8A%E5%AE%8B%E9%9B%A8%E7%90%A6%E7%AB%99%E5%93%A5%E4%BA%86%23","text":"李昀锐当上宋雨琦站哥了","count":158208,"firstSeen":"2026-02-22T03:12:39.865Z","peakCount":158208,"prevCount":0,"velocity":100,"status":"new"},{"url":"/weibo?q=%23%E4%BA%94%E5%8F%B0%E5%B1%B1%E6%98%8E%E7%81%AB%E5%B7%B2%E8%A2%AB%E6%89%91%E7%81%AD%23","text":"五台山明火已被扑灭","count":152667,"firstSeen":"2026-02-22T03:12:39.865Z","peakCount":152667,"prevCount":0,"velocity":100,"status":"new"},{"url":"/weibo?q=%23%E8%8B%A5%E5%86%B3%E8%B5%9B%E5%8F%96%E6%B6%88%E8%B0%B7%E7%88%B1%E5%87%8C%E5%B0%86%E6%97%A0%E7%BC%98%E5%A5%96%E7%89%8C%23","text":"若决赛取消谷爱凌将无缘奖牌","count":125159,"firstSeen":"2026-02-22T03:12:39.865Z","peakCount":125159,"prevCount":0,"velocity":100,"status":"new"},{"url":"/weibo?q=%23%E5%8D%95%E5%B1%8A%E5%86%AC%E5%A5%A5%E4%BC%9A6%E9%87%91%23","text":"单届冬奥会6金","count":124884,"firstSeen":"2026-02-22T03:12:39.865Z","peakCount":124884,"prevCount":0,"velocity":100,"status":"new"},{"url":"/weibo?q=%23%E5%B0%8F%E4%BC%99%E6%92%9E%E6%AF%81%E5%88%9A%E8%BF%98%E6%B8%85%E8%BD%A6%E8%B4%B7%E7%9A%84%E5%AE%9D%E9%A9%AC%E5%BE%AE%E7%AC%91%E5%90%88%E5%BD%B1%23","text":"小伙撞毁刚还清车贷的宝马微笑合影","count":124171,"firstSeen":"2026-02-22T03:12:39.865Z","peakCount":124171,"prevCount":0,"velocity":100,"status":"new"},{"url":"/weibo?q=%23%E5%B0%8F%E4%BC%99%E5%88%9A%E8%BF%98%E6%B8%85%E8%BD%A6%E8%B4%B7%E5%AE%9D%E9%A9%AC%E5%87%A0%E4%B9%8E%E6%92%9E%E6%8A%A5%E5%BA%9F%23","text":"小伙刚还清车贷宝马几乎撞报废","count":122619,"firstSeen":"2026-02-22T03:12:39.865Z","peakCount":122619,"prevCount":0,"velocity":100,"status":"new"},{"url":"/weibo?q=%23%E6%97%B6%E4%BB%A3%E5%B0%91%E5%B9%B4%E5%9B%A2%E6%BC%94%E5%94%B1%E4%BC%9A%23","text":"时代少年团演唱会","count":121731,"firstSeen":"2026-02-22T03:12:39.865Z","peakCount":121731,"prevCount":0,"velocity":100,"status":"new"},{"url":"/weibo?q=%23%E9%95%96%E4%BA%BA%E5%8F%A3%E7%A2%91%E5%8D%87%E8%87%B3%E7%AC%AC%E4%B8%80%23","text":"镖人口碑升至第一","count":120743,"firstSeen":"2026-02-22T03:12:39.865Z","peakCount":120743,"prevCount":0,"velocity":100,"status":"new"},{"url":"/weibo?q=%23%E7%88%B6%E4%BA%B2%E5%B1%8B%E5%A4%96%E9%80%8F%E6%B0%94%E5%81%B6%E9%81%87%E5%84%BF%E5%AD%90%E5%9D%A0%E6%A5%BC%E6%8E%A5%E4%BD%8F%23","text":"父亲屋外透气偶遇儿子坠楼接住","count":120122,"firstSeen":"2026-02-22T03:12:39.865Z","peakCount":120122,"prevCount":0,"velocity":100,"status":"new","textEn":"Father accidentally caught his son after he fell from the building outside his house to get some air."},{"url":"/weibo?q=%23%E5%B0%86%E9%97%A8%E6%AF%92%E5%90%8E%E7%94%A8%E7%A8%8B%E5%B0%91%E5%95%86%E7%9A%84%E4%B8%AA%E4%BA%BA%E6%9B%B2%23","text":"将门毒后用程少商的个人曲","count":119300,"firstSeen":"2026-02-22T03:12:39.865Z","peakCount":119300,"prevCount":0,"velocity":100,"status":"new"},{"url":"/weibo?q=%23%E6%80%95%E6%9C%8B%E5%8F%8B%E8%BF%87%E5%BE%97%E8%8B%A6%E5%8F%88%E6%80%95%E6%9C%8B%E5%8F%8B%E5%BC%80%E8%B7%AF%E8%99%8E%23","text":"怕朋友过得苦又怕朋友开路虎","count":118222,"firstSeen":"2026-02-22T03:12:39.865Z","peakCount":118222,"prevCount":0,"velocity":100,"status":"new"},{"url":"/weibo?q=%23%E6%9D%A8%E6%B4%8B%E6%89%8B%E9%83%A8%E9%AA%A8%E6%8A%98%23","text":"杨洋手部骨折","count":105970,"firstSeen":"2026-02-22T03:12:39.865Z","peakCount":105970,"prevCount":0,"velocity":100,"status":"new"},{"url":"/weibo?q=%23%E5%88%9D%E5%85%AD%23","text":"初六","count":103976,"firstSeen":"2026-02-22T03:12:39.865Z","peakCount":103976,"prevCount":0,"velocity":100,"status":"new"},{"url":"/weibo?q=%23%E5%88%98%E6%A2%A6%E7%AB%A0%E9%BD%90%E6%80%9D%E9%92%A7%E4%BA%A4%E5%BE%80%E7%BA%A66%E5%B9%B4%23","text":"刘梦章齐思钧交往约6年","count":103849,"firstSeen":"2026-02-22T03:12:39.865Z","peakCount":103849,"prevCount":0,"velocity":100,"status":"new"},{"url":"/weibo?q=%23%E7%99%BD%E9%B9%BF%E6%99%92%E8%B7%91%E7%94%B7%E5%9B%A2gidle%E5%90%88%E7%85%A7%23","text":"白鹿晒跑男团gidle合照","count":102367,"firstSeen":"2026-02-22T03:12:39.865Z","peakCount":102367,"prevCount":0,"velocity":100,"status":"new"},{"url":"/weibo?q=%23%E5%86%B3%E8%B5%9B%E6%8E%A8%E8%BF%9F%E8%B0%B7%E7%88%B1%E5%87%8C%E6%9B%B4%E6%96%B0%E7%A4%BE%E5%AA%92%23","text":"决赛推迟谷爱凌更新社媒","count":87970,"firstSeen":"2026-02-22T03:12:39.865Z","peakCount":87970,"prevCount":0,"velocity":100,"status":"new"},{"url":"/weibo?q=%23%E5%81%B6%E9%81%87%E9%A9%AC%E5%98%89%E7%A5%BA%E8%80%83%E9%A9%BE%E7%85%A7%23","text":"偶遇马嘉祺考驾照","count":85981,"firstSeen":"2026-02-22T03:12:39.865Z","peakCount":85981,"prevCount":0,"velocity":100,"status":"new"},{"url":"/weibo?q=%23%E5%B0%8F%E5%85%94%E6%B4%97%E8%84%B8%E5%B0%8F%E5%85%94%E6%91%94%E5%80%92%23","text":"小兔洗脸小兔摔倒","count":83793,"firstSeen":"2026-02-22T03:12:39.865Z","peakCount":83793,"prevCount":0,"velocity":100,"status":"new"},{"url":"/weibo?q=%23%E6%98%9F%E6%B2%B3%E5%85%A5%E6%A2%A6%E7%A5%A8%E6%88%BF%E4%BD%8E%E8%BF%B7%E4%BB%85%E6%98%AF%E6%8E%92%E7%89%87%E9%97%AE%E9%A2%98%E5%90%97%23","text":"星河入梦票房低迷仅是排片问题吗","count":83696,"firstSeen":"2026-02-22T03:12:39.865Z","peakCount":83696,"prevCount":0,"velocity":100,"status":"new","textEn":"Is the sluggish box office performance of \"Stars in the Sky\" just a matter of film schedule?"},{"url":"/weibo?q=%23%E6%9D%B0%E4%BC%A6%E6%A0%BC%E6%9E%97%E5%8F%8C%E5%8A%A0%E6%97%B6%E7%BB%9D%E6%9D%80%E9%AD%94%E6%9C%AF%23","text":"杰伦格林双加时绝杀魔术","count":66569,"firstSeen":"2026-02-22T03:12:39.865Z","peakCount":66569,"prevCount":0,"velocity":100,"status":"new"},{"url":"/weibo?q=%23%E5%B0%8F%E5%9F%8E%E8%89%AF%E6%96%B9%23","text":"小城良方","count":65926,"firstSeen":"2026-02-22T03:12:39.865Z","peakCount":65926,"prevCount":0,"velocity":100,"status":"new"},{"url":"/weibo?q=%23%E5%AE%81%E5%BF%A0%E5%B2%A9%E7%9B%B4%E6%92%AD%E6%99%92%E4%B8%89%E6%9E%9A%E5%86%AC%E5%A5%A5%E5%A5%96%E7%89%8C%23","text":"宁忠岩直播晒三枚冬奥奖牌","count":64675,"firstSeen":"2026-02-22T03:12:39.865Z","peakCount":64675,"prevCount":0,"velocity":100,"status":"new"},{"url":"/weibo?q=%23%E6%B3%B0%E5%9B%BD%E5%AE%98%E6%96%B9%E9%80%9A%E6%8A%A5%E6%B8%85%E8%BF%8872%E5%8F%AA%E8%80%81%E8%99%8E%E6%AD%BB%E4%BA%A1%23","text":"泰国官方通报清迈72只老虎死亡","count":64243,"firstSeen":"2026-02-22T03:12:39.865Z","peakCount":64243,"prevCount":0,"velocity":100,"status":"new"},{"url":"/weibo?q=%23%E5%8D%81%E5%B9%B4%E5%90%8E%E7%9A%84%E6%81%8B%E7%88%B1%E5%85%B3%E7%B3%BB%23","text":"十年后的恋爱关系","count":62757,"firstSeen":"2026-02-22T03:12:39.865Z","peakCount":62757,"prevCount":0,"velocity":100,"status":"new"},{"url":"/weibo?q=%23%E5%A4%9C%E7%8E%8B%23","text":"夜王","count":62575,"firstSeen":"2026-02-22T03:12:39.865Z","peakCount":62575,"prevCount":0,"velocity":100,"status":"new"},{"url":"/weibo?q=%23%E4%BC%8A%E8%83%BD%E9%9D%99%E8%A1%A3%E6%9C%8D%E5%90%8A%E7%89%8C%E6%B2%A1%E6%91%98%23","text":"伊能静衣服吊牌没摘","count":171955,"firstSeen":"2026-02-21T23:27:43.919Z","peakCount":171955,"prevCount":70093,"velocity":145,"status":"rising"},{"url":"/weibo?q=%23%E9%BD%90%E6%80%9D%E9%92%A7%E5%9B%9E%E5%BA%94%E5%88%86%E6%89%8B%23","text":"齐思钧回应分手","count":168456,"textEn":"Qi Sijun responded to the breakup","firstSeen":"2026-02-21T16:41:23.203Z","peakCount":168456,"prevCount":106080,"velocity":59,"status":"rising"},{"url":"/weibo?q=%23%E6%AF%8F%E5%A4%A9%E6%97%A9%E7%9D%A11%E5%B0%8F%E6%97%B6%E8%BA%AB%E4%BD%93%E5%B0%B1%E4%B8%8D%E4%B8%80%E6%A0%B7%23","text":"每天早睡1小时身体就不一样","count":117418,"firstSeen":"2026-02-21T23:49:29.113Z","peakCount":117418,"prevCount":70835,"velocity":66,"status":"rising"},{"url":"/weibo?q=%23%E5%A8%B1%E4%B9%90%E5%9C%88%E6%81%8B%E7%88%B1%E5%B0%B1%E6%98%AF%E4%B8%80%E4%B8%AA%E5%B7%A8%E5%A4%A7%E7%9A%84%E5%8E%BF%E5%9F%8E%E6%96%87%E5%AD%A6%23","text":"娱乐圈恋爱就是一个巨大的县城文学","count":116896,"firstSeen":"2026-02-21T23:49:29.113Z","peakCount":116896,"prevCount":68636,"velocity":70,"status":"rising"},{"url":"/weibo?q=%23%E7%83%AD%E6%B0%94%E8%85%BE%E8%85%BE%E7%9A%84%E4%B8%AD%E5%9B%BD%E5%B9%B4%23","text":"热气腾腾的中国年","count":656063,"textEn":"Steamy Chinese New Year","firstSeen":"2026-02-21T16:41:23.203Z","peakCount":656063,"prevCount":581831,"velocity":13,"status":"hot"},{"url":"/weibo?q=%23%E5%B0%86%E9%97%A8%E7%8B%AC%E5%90%8E%E5%88%86%E9%94%80%E7%BA%A2%E6%9E%9C%23","text":"将门独后分销红果","count":85486,"textEn":"The only queen in the family distributes red fruits","firstSeen":"2026-02-22T00:01:15.318Z","peakCount":85486,"prevCount":79758,"velocity":7,"status":"hot"},{"url":"/weibo?q=%23%E8%8B%8F%E7%BF%8A%E9%B8%A3%E9%97%AD%E5%B9%95%E5%BC%8F%E6%97%97%E6%89%8B%23","text":"苏翊鸣闭幕式旗手","count":68542,"textEn":"Su Yiming flag bearer at closing ceremony","firstSeen":"2026-02-21T18:45:23.837Z","peakCount":105006,"prevCount":71402,"velocity":-4,"status":"hot"},{"url":"/weibo?q=%23%E9%95%96%E4%BA%BA%23","text":"镖人","count":66248,"textEn":"escort","firstSeen":"2026-02-21T16:41:23.203Z","peakCount":286673,"prevCount":59500,"velocity":11,"status":"hot"},{"url":"/weibo?q=%23%E4%BB%8A%E5%B9%B4%E5%A5%BD%E5%87%A0%E5%AF%B9%E6%83%85%E4%BE%A3%E9%83%BD%E5%88%86%E4%BA%86%23","text":"今年好几对情侣都分了","count":65037,"textEn":"Several couples have broken up this year","firstSeen":"2026-02-21T16:41:23.203Z","peakCount":91261,"prevCount":70983,"velocity":-8,"status":"hot"},{"url":"/weibo?q=%23%E5%89%8D%E6%96%B9%E6%97%A0%E5%8E%95%E6%89%80%E6%97%A0%E7%83%A4%E8%82%A0%E6%97%A0%E8%8C%B6%E5%8F%B6%E8%9B%8B%23","text":"前方无厕所无烤肠无茶叶蛋","count":79571,"textEn":"No toilet ahead, no sausages, no tea eggs","firstSeen":"2026-02-21T16:41:23.203Z","peakCount":1049660,"prevCount":1049660,"velocity":-92,"status":"falling"},{"url":"/weibo?q=%23%E7%BE%8E%E9%AB%98%E5%AE%98%E5%8F%AB%E5%9A%A327%E5%88%86%E9%92%9F%E6%8E%A5%E6%88%98%E5%8F%B0%E6%B5%B7%23","text":"美高官叫嚣27分钟接战台海","count":65383,"textEn":"Senior U.S. officials clamor for war over Taiwan in 27 minutes","firstSeen":"2026-02-21T23:49:29.113Z","peakCount":249183,"prevCount":249183,"velocity":-74,"status":"falling"},{"url":"/weibo?q=%23%E7%BB%93%E5%A9%9A%E4%BA%94%E9%87%91%E8%B5%B7%E6%AD%A5%E4%BB%B7%E8%BF%88%E5%85%A510%E4%B8%87%E5%85%83%E5%A4%A7%E5%85%B3%23","text":"结婚五金起步价迈入10万元大关","count":64469,"textEn":"The starting price of wedding hardware has reached the 100,000 yuan mark","firstSeen":"2026-02-21T16:41:23.203Z","peakCount":96967,"prevCount":89362,"velocity":-28,"status":"falling"},{"url":"/weibo?q=%23%E8%B0%B7%E7%88%B1%E5%87%8CU%E5%9E%8B%E5%9C%BA%E5%9C%B0%E5%86%B3%E8%B5%9B%E6%8E%A8%E8%BF%9F%23","text":"谷爱凌U型场地决赛推迟","count":734849,"textEn":"Gu Ailing's U-shaped field final postponed","firstSeen":"2026-02-21T17:02:28.872Z","peakCount":948643,"prevCount":734849,"velocity":-100,"status":"gone"},{"url":"/weibo?q=%23%E7%8E%8B%E4%BC%A0%E5%90%9B%E5%BD%95%E7%BB%BC%E8%89%BA%E5%B4%A9%E6%BA%83%E7%88%86%E5%93%AD%23","text":"王传君录综艺崩溃爆哭","count":349727,"textEn":"Wang Chuanjun's variety show collapsed and burst into tears","firstSeen":"2026-02-21T16:41:23.203Z","peakCount":349727,"prevCount":349727,"velocity":-100,"status":"gone"},{"url":"/weibo?q=%23%E5%A6%88%E7%A5%96%23","text":"妈祖","count":297333,"firstSeen":"2026-02-21T23:27:43.919Z","peakCount":297333,"prevCount":297333,"velocity":-100,"status":"gone"},{"url":"/weibo?q=%23%E4%BA%94%E5%8F%B0%E5%B1%B1%E6%99%AF%E5%8C%BA%E7%AA%81%E5%8F%91%E7%81%AB%E6%83%85%23","text":"五台山景区突发火情","count":202730,"firstSeen":"2026-02-21T23:49:29.113Z","peakCount":202730,"prevCount":202730,"velocity":-100,"status":"gone"},{"url":"/weibo?q=%23%E7%99%BD%E9%B9%BF%20%E6%88%91%E5%AE%B6923%23","text":"白鹿 我家923","count":126337,"textEn":"Bailu my home 923","firstSeen":"2026-02-21T16:41:23.203Z","peakCount":359597,"prevCount":126337,"velocity":-100,"status":"gone"},{"url":"/weibo?q=%23%E6%B8%B8%E5%AE%A2%E6%8C%A4%E5%88%B0%E6%82%94%E4%B8%8D%E5%BD%93%E5%88%9D%E4%B8%8D%E5%A6%82%E5%9C%A8%E5%AE%B6%E5%88%B7%E6%89%8B%E6%9C%BA%23","text":"游客挤到悔不当初不如在家刷手机","count":123463,"textEn":"Tourists are so crowded that I regret that I would rather check my phone at home","firstSeen":"2026-02-21T16:41:23.203Z","peakCount":148821,"prevCount":123463,"velocity":-100,"status":"gone"},{"url":"/weibo?q=%23%E8%BE%BD%E5%AE%81%E6%98%A5%E6%99%9A%E6%9C%80%E5%A4%A7%E9%BB%91%E9%A9%AC%E5%B0%8F%E5%93%81%E4%BB%A5%E8%B2%8C%E5%8F%96%E4%BA%BA%23","text":"辽宁春晚最大黑马小品以貌取人","count":109024,"textEn":"The biggest dark horse sketch of Liaoning Spring Festival Gala judges people by their appearance","firstSeen":"2026-02-21T16:41:23.203Z","peakCount":145594,"prevCount":109024,"velocity":-100,"status":"gone"},{"url":"/weibo?q=%23%E7%9F%B3%E5%AE%B6%E5%BA%84%E5%B1%B1%E7%81%AB%23","text":"石家庄山火","count":101315,"textEn":"Shijiazhuang mountain fire","firstSeen":"2026-02-21T23:27:43.919Z","peakCount":101315,"prevCount":101315,"velocity":-100,"status":"gone"},{"url":"/weibo?q=%23%E8%B4%9D%E5%8A%A0%E5%B0%94%E6%B9%96%E4%B8%AD%E5%9B%BD%E6%B8%B8%E5%AE%A2%E9%81%87%E9%9A%BE%E7%82%B9%E6%97%81%E5%86%8D%E7%8E%B0%E4%BA%8B%E6%95%85%23","text":"贝加尔湖中国游客遇难点旁再现事故","count":97755,"textEn":"Accident reappears near Lake Baikal where Chinese tourist died","firstSeen":"2026-02-21T23:27:43.919Z","peakCount":97755,"prevCount":97755,"velocity":-100,"status":"gone"},{"url":"/weibo?q=%23%E5%88%98%E6%B6%9B%E5%9B%9E%E5%BA%94%E5%A6%88%E7%A5%96%E7%85%A7%E8%A2%AB%E8%AE%BE%E4%B8%BA%E5%B1%8F%E4%BF%9D%23","text":"刘涛回应妈祖照被设为屏保","count":95709,"textEn":"Liu Tao responded to Mazu’s photo being set as a screensaver","firstSeen":"2026-02-21T16:41:23.203Z","peakCount":118688,"prevCount":95709,"velocity":-100,"status":"gone"},{"url":"/weibo?q=%23%E6%9D%8E%E4%B9%A6%E5%90%8D%2026%E5%B2%81%E5%A5%B3%E6%88%BF%E5%AE%A2%23","text":"李书名 26岁女房客","count":88492,"textEn":"Li Shuming, 26-year-old female tenant","firstSeen":"2026-02-21T16:41:23.203Z","peakCount":115539,"prevCount":88492,"velocity":-100,"status":"gone"},{"url":"/weibo?q=%23%E9%AB%98%E6%95%8F%E6%84%9F%E4%BA%BA%E4%B8%80%E7%94%9F%E7%9A%84%E4%B8%BB%E7%BA%BF%E4%BB%BB%E5%8A%A1%23","text":"高敏感人一生的主线任务","count":81670,"textEn":"The main task of a highly sensitive person’s life","firstSeen":"2026-02-21T16:41:23.203Z","peakCount":84176,"prevCount":81670,"velocity":-100,"status":"gone"},{"url":"/weibo?q=%23%E6%9D%8E%E6%98%80%E9%94%90%E6%8B%8D%E5%AE%8B%E9%9B%A8%E7%90%A6%23","text":"李昀锐拍宋雨琦","count":81041,"textEn":"Li Yunrui shoots Song Yuqi","firstSeen":"2026-02-21T16:41:23.203Z","peakCount":147671,"prevCount":81041,"velocity":-100,"status":"gone"},{"url":"/weibo?q=%23%E5%BE%90%E6%A2%A6%E6%A1%83%E7%AC%91%E7%A7%B0%E8%BF%99%E6%98%AF%E7%AC%AC%E4%B8%80%E6%9E%9A%E5%A5%A5%E8%BF%90%E9%93%9C%E7%89%8C%23","text":"徐梦桃笑称这是第一枚奥运铜牌","count":76834,"firstSeen":"2026-02-21T16:41:23.203Z","peakCount":76834,"prevCount":76834,"velocity":-100,"status":"gone","textEn":"Xu Mengtao laughed and said this was the first Olympic bronze medal"},{"url":"/weibo?q=%23%E5%BE%8B%E5%B8%88%E8%A7%A3%E8%AF%BB15%E5%B2%81%E5%A5%B3%E5%AD%A9%E8%A2%AB%E5%BD%93%E8%A1%97%E6%9A%B4%E6%89%93%E4%BA%8B%E4%BB%B6%23","text":"律师解读15岁女孩被当街暴打事件","count":74247,"textEn":"Lawyer explains the incident of a 15-year-old girl being beaten in the street","firstSeen":"2026-02-21T16:41:23.203Z","peakCount":533596,"prevCount":74247,"velocity":-100,"status":"gone"},{"url":"/weibo?q=%23%E6%9D%8E%E5%A4%A9%E9%A9%AC%E5%9B%9E%E5%BA%94%E5%A4%B1%E8%AF%AF%23","text":"李天马回应失误","count":73841,"firstSeen":"2026-02-21T16:41:23.203Z","peakCount":92272,"prevCount":73841,"velocity":-100,"status":"gone","textEn":"Li Tianma responded incorrectly"},{"url":"/weibo?q=%23%E9%BD%90%E6%80%9D%E9%92%A7%E5%88%98%E6%A2%A6%E7%AB%A0%E5%88%86%E6%89%8B%E5%90%8E%E8%BF%98%E8%83%BD%E5%8F%8B%E5%A5%BD%E5%90%8C%E6%B8%B8%23","text":"齐思钧刘梦章分手后还能友好同游","count":71171,"firstSeen":"2026-02-21T23:49:29.113Z","peakCount":71171,"prevCount":71171,"velocity":-100,"status":"gone"},{"url":"/weibo?q=%23%E9%A3%9E%E9%A9%B0%E4%BA%BA%E7%94%9F3%E5%9C%A8%E8%8C%83%E4%B8%9E%E4%B8%9E%E5%AE%B6%E4%B9%A1%E6%8B%8D%E7%9A%84%23","text":"飞驰人生3在范丞丞家乡拍的","count":70677,"firstSeen":"2026-02-21T23:49:29.113Z","peakCount":70677,"prevCount":70677,"velocity":-100,"status":"gone"},{"url":"/weibo?q=%23%E5%88%9D%E5%85%AD%E9%80%81%E7%A9%B7%E6%80%8E%E4%B9%88%E9%80%81%23","text":"初六送穷怎么送","count":68885,"textEn":"How to send money to the poor on the sixth day of the Lunar New Year?","firstSeen":"2026-02-21T16:41:23.203Z","peakCount":90806,"prevCount":68885,"velocity":-100,"status":"gone"},{"url":"/weibo?q=%23%E5%B0%8F%E4%BC%99%E6%92%95%E5%8E%BB%E5%B9%B4%E5%AF%B9%E8%81%94%E5%A4%A9%E5%A1%8C%E4%BA%86%23","text":"小伙撕去年对联天塌了","count":67464,"firstSeen":"2026-02-21T23:49:29.113Z","peakCount":67464,"prevCount":67464,"velocity":-100,"status":"gone"},{"url":"/weibo?q=%23%E4%B8%8A%E9%97%A8%E5%96%82%E7%8C%AB%E4%B8%8D%E8%AE%A9%E4%BA%BA%E8%B5%B0%23","text":"上门喂猫不让人走","count":59763,"textEn":"Feed the cat at your door and won't let it go","firstSeen":"2026-02-21T16:41:23.203Z","peakCount":121348,"prevCount":59763,"velocity":-100,"status":"gone"},{"url":"/weibo?q=%23%E9%AD%8F%E5%A4%A7%E5%8B%8B%E4%B8%8D%E5%9C%A8%E5%A4%A7%E4%BE%A6%E6%8E%A2%E7%BE%A4%E9%87%8C%23","text":"魏大勋不在大侦探群里","count":56911,"firstSeen":"2026-02-21T23:27:43.919Z","peakCount":56911,"prevCount":56911,"velocity":-100,"status":"gone"},{"url":"/weibo?q=%23%E6%BB%91%E9%9B%AA%E6%AF%94%E8%B5%9B%E4%B8%BA%E5%95%A5%E9%9D%9E%E5%BE%97%E5%B8%A6%E6%89%8B%E6%9C%BA%23","text":"滑雪比赛为啥非得带手机","count":55936,"textEn":"Why do you have to bring a mobile phone to ski competitions?","firstSeen":"2026-02-21T17:56:52.458Z","peakCount":55936,"prevCount":55936,"velocity":-100,"status":"gone"},{"url":"/weibo?q=%23%E4%BA%BA%E7%94%9F%E5%8E%BB%E7%95%99%23","text":"人生去留","count":55816,"textEn":"Stay or leave in life","firstSeen":"2026-02-21T17:02:28.872Z","peakCount":121629,"prevCount":55816,"velocity":-100,"status":"gone"},{"url":"/weibo?q=%23%E6%9D%8E%E6%99%A8%E5%8F%91%E8%B7%91%E7%94%B7%E5%9B%A2idle%E5%90%88%E7%85%A7%23","text":"李晨发跑男团idle合照","count":54039,"firstSeen":"2026-02-21T16:41:23.203Z","peakCount":114704,"prevCount":54039,"velocity":-100,"status":"gone"},{"url":"/weibo?q=%23%E6%9B%9D%E9%BD%90%E6%80%9D%E9%92%A7%E5%88%98%E6%A2%A6%E7%AB%A0%E5%88%86%E6%89%8B%23","text":"曝齐思钧刘梦章分手","count":51921,"textEn":"Qi Sijun and Liu Mengzhang's breakup exposed","firstSeen":"2026-02-21T16:41:23.203Z","peakCount":91721,"prevCount":51921,"velocity":-100,"status":"gone"},{"url":"/weibo?q=%23%E8%B0%B7%E7%88%B1%E5%87%8C%E5%86%B3%E8%B5%9B%E6%97%B6%E9%97%B4%23","text":"谷爱凌决赛时间","count":49454,"textEn":"Gu Ailing final time","firstSeen":"2026-02-21T19:13:55.552Z","peakCount":72943,"prevCount":49454,"velocity":-100,"status":"gone"},{"url":"/weibo?q=%23%E5%8C%97%E4%BA%AC%E6%B2%99%E5%B0%98%E6%9A%B4%E8%87%B4%E5%A4%A7%E5%85%B4%E6%9C%BA%E5%9C%BA%E5%A4%9A%E8%B6%9F%E8%88%AA%E7%8F%AD%E5%A4%87%E9%99%8D%23","text":"北京沙尘暴致大兴机场多趟航班备降","count":46872,"textEn":"Sandstorm in Beijing caused multiple flights to divert at Daxing Airport","firstSeen":"2026-02-21T16:41:23.203Z","peakCount":92626,"prevCount":46872,"velocity":-100,"status":"gone"},{"url":"/weibo?q=%23%E7%8E%8B%E5%BF%83%E8%BF%AA%E8%A6%81%E9%99%AA%E5%BE%90%E6%A2%A6%E6%A1%83%E5%85%AD%E6%88%98%E5%86%AC%E5%A5%A5%23","text":"王心迪要陪徐梦桃六战冬奥","count":45883,"firstSeen":"2026-02-21T23:49:29.113Z","peakCount":45883,"prevCount":45883,"velocity":-100,"status":"gone"},{"url":"/weibo?q=%23%E8%BA%AB%E4%BD%935%E4%B8%AA%E8%A1%A8%E7%8E%B0%E8%AF%B4%E6%98%8E%E9%9C%80%E8%A6%81%E9%99%A4%E6%B9%BF%E4%BA%86%23","text":"身体5个表现说明需要除湿了","count":45696,"textEn":"5 signs your body needs dehumidification","firstSeen":"2026-02-21T16:41:23.203Z","peakCount":83441,"prevCount":45696,"velocity":-100,"status":"gone"},{"url":"/weibo?q=%23%E5%B0%86%E9%97%A8%E6%AF%92%E5%90%8E%23","text":"将门毒后","count":45688,"textEn":"After poisoning the door","firstSeen":"2026-02-21T16:41:23.203Z","peakCount":123049,"prevCount":45688,"velocity":-100,"status":"gone"},{"url":"/weibo?q=%23%E5%A5%B3%E8%B4%A2%E7%A5%9E%E8%A2%AB%E6%B8%B8%E5%AE%A2%E8%BF%BD%E5%BE%97%E6%BB%A1%E5%9C%BA%E8%B7%91%23","text":"女财神被游客追得满场跑","count":45536,"textEn":"The female Goddess of Wealth was chased all over the place by tourists","firstSeen":"2026-02-21T16:41:23.203Z","peakCount":80921,"prevCount":45536,"velocity":-100,"status":"gone"},{"url":"/weibo?q=%23%E5%88%98%E6%A2%A6%E7%AB%A0%E7%A7%B0%E4%B8%8D%E5%AD%98%E5%9C%A8%E5%87%BA%E8%BD%A8%23","text":"刘梦章称不存在出轨","count":45408,"textEn":"Liu Mengzhang said there was no cheating","firstSeen":"2026-02-21T16:41:23.203Z","peakCount":89382,"prevCount":45408,"velocity":-100,"status":"gone"},{"url":"/weibo?q=%23%E6%95%96%E7%91%9E%E9%B9%8F%E6%B2%88%E7%BE%BD%E6%B4%81%E6%B5%B4%E5%AE%A4%E6%B9%BF%E8%BA%AB%E6%88%8F%23","text":"敖瑞鹏沈羽洁浴室湿身戏","count":43465,"firstSeen":"2026-02-21T16:41:23.203Z","peakCount":79395,"prevCount":43465,"velocity":-100,"status":"gone"},{"url":"/weibo?q=%23%E5%BC%A0%E5%BD%AC%E5%BD%AC%E5%89%83%E4%BA%86%E5%AF%B8%E5%A4%B4%23","text":"张彬彬剃了寸头","count":43241,"firstSeen":"2026-02-21T16:41:23.203Z","peakCount":78747,"prevCount":43241,"velocity":-100,"status":"gone","textEn":"Zhang Binbin shaved his head"},{"url":"/weibo?q=%23%E7%8E%8B%E6%A5%9A%E9%92%A6%E5%AD%99%E9%A2%96%E8%8E%8E%E5%85%A5%E5%9C%BA%E5%8F%97%E5%88%B0%E7%83%AD%E7%83%88%E6%AC%A2%E8%BF%8E%23","text":"王楚钦孙颖莎入场受到热烈欢迎","count":43029,"firstSeen":"2026-02-21T16:41:23.203Z","peakCount":77456,"prevCount":43029,"velocity":-100,"status":"gone","textEn":"Wang Chuqin and Sun Yingsha received a warm welcome when entering the venue"},{"url":"/weibo?q=%23%E4%BD%99%E6%89%BF%E6%81%A9%E5%85%A8%E5%AE%B6%E7%9B%B4%E6%8E%A5%E5%BC%80%E5%90%AF%E5%86%9B%E8%AE%AD%E6%A8%A1%E5%BC%8F%23","text":"余承恩全家直接开启军训模式","count":42549,"firstSeen":"2026-02-21T16:41:23.203Z","peakCount":97361,"prevCount":42549,"velocity":-100,"status":"gone","textEn":"Yu Chengen and his family directly started military training mode"},{"url":"/weibo?q=%23%E5%BE%90%E6%A2%A6%E6%A1%83%E5%AE%89%E6%85%B0%E6%9D%8E%E5%A4%A9%E9%A9%AC%E7%8E%8B%E5%BF%83%E8%BF%AA%E5%90%83%E9%86%8B%23","text":"徐梦桃安慰李天马王心迪吃醋","count":40495,"firstSeen":"2026-02-21T16:41:23.203Z","peakCount":78967,"prevCount":40495,"velocity":-100,"status":"gone","textEn":"Xu Mengtao consoles Li Tianma and Wang Xindi for being jealous"},{"url":"/weibo?q=%23%E5%A4%A7%E5%B9%B4%E5%88%9D%E5%85%AD%23","text":"大年初六","count":39683,"textEn":"The sixth day of the Lunar New Year","firstSeen":"2026-02-21T17:37:21.189Z","peakCount":180352,"prevCount":39683,"velocity":-100,"status":"gone"},{"url":"/weibo?q=%23%E5%BE%90%E7%92%90%E9%80%8F%E9%9C%B2%E7%9B%AE%E5%89%8D%E4%BD%93%E9%87%8D%E4%B8%BA96%E6%96%A4%23","text":"徐璐透露目前体重为96斤","count":39525,"textEn":"Xu Lu revealed that her current weight is 96 pounds","firstSeen":"2026-02-21T16:41:23.203Z","peakCount":81100,"prevCount":39525,"velocity":-100,"status":"gone"},{"url":"/weibo?q=%23%E4%B8%93%E5%AE%B6%E6%8F%90%E9%86%92%E8%BF%87%E6%9C%9F%E8%8D%AF%E5%AE%B3%E7%8C%9B%E5%A6%82%E8%99%8E%23","text":"专家提醒过期药害猛如虎","count":39367,"textEn":"Experts warn that expired medicines can be as harmful as tigers","firstSeen":"2026-02-21T16:41:23.203Z","peakCount":90124,"prevCount":39367,"velocity":-100,"status":"gone"},{"url":"/weibo?q=%23%E9%A9%AC%E5%B9%B4%E4%B8%8D%E5%AE%9C%E5%A9%9A%E5%AB%81%E6%98%AF%E6%97%A0%E7%A8%BD%E4%B9%8B%E8%B0%88%23","text":"马年不宜婚嫁是无稽之谈","count":38803,"textEn":"It is nonsense to say that it is not suitable to get married in the Year of the Horse.","firstSeen":"2026-02-21T19:13:55.552Z","peakCount":53606,"prevCount":38803,"velocity":-100,"status":"gone"},{"url":"/weibo?q=%23%E5%A5%B3%E5%AD%90%E5%B0%86900%E5%85%8B%E9%BB%84%E9%87%91%E9%81%97%E5%BF%98%E5%8A%A8%E8%BD%A6%E5%BD%93%E5%9C%BA%E5%90%93%E6%99%95%23","text":"女子将900克黄金遗忘动车当场吓晕","count":38641,"firstSeen":"2026-02-21T16:41:23.203Z","peakCount":91843,"prevCount":38641,"velocity":-100,"status":"gone"},{"url":"/weibo?q=%23%E5%94%90%E5%AE%AB%E5%A5%87%E6%A1%88%23","text":"唐宫奇案","count":37854,"textEn":"Strange Cases in the Tang Palace","firstSeen":"2026-02-21T19:40:27.558Z","peakCount":37854,"prevCount":37854,"velocity":-100,"status":"gone"},{"url":"/weibo?q=%23%E8%B0%B7%E7%88%B1%E5%87%8C%E7%B1%B3%E5%85%B0%E5%86%AC%E5%A5%A5%E6%94%B6%E5%AE%98%E6%88%98%23","text":"谷爱凌米兰冬奥收官战","count":37836,"textEn":"Gu Ailing Milan Winter Olympics final match","firstSeen":"2026-02-21T17:02:28.872Z","peakCount":74086,"prevCount":37836,"velocity":-100,"status":"gone"},{"url":"/weibo?q=%23%E5%91%A8%E6%B7%B1%E4%BA%94%E5%A4%A9%E5%87%BA%E4%BA%86%E4%B8%89%E9%A6%96%E5%A5%BD%E8%BF%90%E6%AD%8C%E6%9B%B2%23","text":"周深五天出了三首好运歌曲","count":37825,"textEn":"Three good luck songs were released in the five days of Zhou Shen","firstSeen":"2026-02-21T20:29:50.638Z","peakCount":37825,"prevCount":37825,"velocity":-100,"status":"gone"},{"url":"/weibo?q=%23%E5%88%98%E6%B5%A9%E5%AD%98%E5%88%9D%E4%BA%94%E8%BF%8E%E8%B4%A2%E7%A5%9E%E8%87%AA%E6%8B%8D%23","text":"刘浩存初五迎财神自拍","count":37813,"textEn":"Liu Haocun takes a selfie on the fifth day of the Lunar New Year to welcome the God of Wealth","firstSeen":"2026-02-21T16:41:23.203Z","peakCount":79568,"prevCount":37813,"velocity":-100,"status":"gone"},{"url":"/weibo?q=%23%E4%B8%AD%E5%9B%BD%E9%98%9F%E7%A9%BA%E4%B8%AD%E6%8A%80%E5%B7%A7%E6%B7%B7%E5%9B%A2%E9%93%9C%E7%89%8C%23","text":"中国队空中技巧混团铜牌","count":37804,"textEn":"Chinese team aerials mixed team bronze medal","firstSeen":"2026-02-21T16:41:23.203Z","peakCount":80388,"prevCount":37804,"velocity":-100,"status":"gone"},{"url":"/weibo?q=%23%E5%90%AC%E5%AE%8C%E4%B8%80%E7%82%B9%E4%B9%9F%E4%B8%8D%E6%83%B3%E5%8E%BB%E9%9C%8D%E6%A0%BC%E6%B2%83%E5%85%B9%E4%BA%86%23","text":"听完一点也不想去霍格沃兹了","count":37797,"firstSeen":"2026-02-22T00:01:15.318Z","peakCount":37797,"prevCount":37797,"velocity":-100,"status":"gone"},{"url":"/weibo?q=%23%E8%8C%83%E4%B8%9E%E4%B8%9E%E6%9D%8E%E6%98%80%E9%94%90%E7%BB%99%E5%AE%8B%E9%9B%A8%E7%90%A6%E4%B8%BE%E6%89%8B%E5%B9%85%23","text":"范丞丞李昀锐给宋雨琦举手幅","count":37791,"textEn":"Fan Chengcheng and Li Yunrui raised their hands to Song Yuqi","firstSeen":"2026-02-21T16:41:23.203Z","peakCount":90203,"prevCount":37791,"velocity":-100,"status":"gone"},{"url":"/weibo?q=%23%E7%8E%8B%E5%8A%9B%E5%AE%8F%E5%85%B3%E4%BA%8E%E5%A4%A7%E5%90%8C%E7%9A%84%E5%BD%B1%E7%89%87%23","text":"王力宏关于大同的影片","count":37766,"textEn":"Leehom Wang’s video about Datong","firstSeen":"2026-02-21T18:45:23.837Z","peakCount":37766,"prevCount":37766,"velocity":-100,"status":"gone"}]