[{"url":"/weibo?q=%23%E5%90%AC%E8%AF%B4%E5%85%A8%E5%9B%BD%E5%A5%B3%E5%A9%BF%E5%88%B0%E4%B8%88%E6%AF%8D%E5%A8%98%E5%AE%B6%E9%83%BD%E8%BF%99%E6%A0%B7%23","text":"听说全国女婿到丈母娘家都这样","count":795411,"firstSeen":"2026-02-18T06:16:09.815Z","peakCount":795411,"prevCount":0,"velocity":100,"status":"new","textEn":"I heard that this happens all over the country when a son-in-law goes to his mother-in-law’s house."},{"url":"/weibo?q=%23%E6%88%90%E9%BE%99%E8%BF%99%E9%A6%96%E6%81%AD%E5%96%9C%E8%87%AA%E5%B7%B1%E5%90%AC%E5%93%AD%E4%BA%86%23","text":"成龙这首恭喜自己听哭了","count":601287,"firstSeen":"2026-02-18T06:16:09.815Z","peakCount":601287,"prevCount":0,"velocity":100,"status":"new"},{"url":"/weibo?q=%23%E7%94%A8%E5%8D%83%E9%97%AE%E4%B8%80%E5%8F%A5%E8%AF%9D%E4%B8%8B%E5%8D%95%E6%AF%8F%E6%97%A5%E9%A6%96%E5%8D%95%E5%BF%85%E5%87%8F%23","text":"用千问一句话下单每日首单必减","count":321466,"firstSeen":"2026-02-18T06:16:09.815Z","peakCount":321466,"prevCount":0,"velocity":100,"status":"new"},{"url":"/weibo?q=%23%E9%BE%99%E6%B4%8B%E4%B8%BB%E6%8C%81%E5%AE%8C%E6%98%A5%E6%99%9A%E5%93%AD%E4%BA%86%23","text":"龙洋主持完春晚哭了","count":290449,"firstSeen":"2026-02-18T06:16:09.815Z","peakCount":290449,"prevCount":0,"velocity":100,"status":"new"},{"url":"/weibo?q=%23%E8%BF%87%E5%B9%B4%E4%B8%8D%E8%A6%81%E4%B8%80%E7%9B%B4%E7%A9%BF%E7%9D%A1%E8%A1%A3%23","text":"过年不要一直穿睡衣","count":289269,"firstSeen":"2026-02-18T06:16:09.815Z","peakCount":289269,"prevCount":0,"velocity":100,"status":"new"},{"url":"/weibo?q=%23%E8%B1%86%E5%8C%85%E6%89%93%E9%BA%BB%E5%B0%86%23","text":"豆包打麻将","count":231374,"firstSeen":"2026-02-18T06:16:09.815Z","peakCount":231374,"prevCount":0,"velocity":100,"status":"new"},{"url":"/weibo?q=%23%E5%AE%8B%E5%B0%8F%E5%AE%9D%20%E6%8E%89%E5%BE%AE%E5%8D%9A%E7%83%AD%E6%90%9C%E6%B1%A0%E9%87%8C%E4%BA%86%E6%95%91%E6%95%91%E6%88%91%23","text":"宋小宝 掉微博热搜池里了救救我","count":140680,"firstSeen":"2026-02-18T06:16:09.815Z","peakCount":140680,"prevCount":0,"velocity":100,"status":"new"},{"url":"/weibo?q=%23%E9%AB%98%E5%B8%82%E6%97%A9%E8%8B%97%E5%9F%BA%E6%9C%AC%E7%A1%AE%E5%AE%9A%E5%BD%93%E9%80%89%E6%97%A5%E6%9C%AC%E6%96%B0%E4%BB%BB%E9%A6%96%E7%9B%B8%23","text":"高市早苗基本确定当选日本新任首相","count":140593,"firstSeen":"2026-02-18T06:16:09.815Z","peakCount":140593,"prevCount":0,"velocity":100,"status":"new"},{"url":"/weibo?q=%23%E5%9B%BD%E5%A4%96%E9%95%BF%E5%A4%A7%E7%9A%84%E4%B8%AD%E5%9B%BD%E5%A8%83%E5%9B%9E%E8%80%81%E5%AE%B6%E8%BF%87%E5%B9%B4%E5%8F%8D%E5%BA%94%E4%BA%AE%E4%BA%86%23","text":"国外长大的中国娃回老家过年反应亮了","count":115900,"firstSeen":"2026-02-18T06:16:09.815Z","peakCount":115900,"prevCount":0,"velocity":100,"status":"new"},{"url":"/weibo?q=%23%E4%BB%8A%E5%B9%B4%E8%BF%87%E5%B9%B4%E6%B2%A1%E4%BA%BA%E5%82%AC%E5%A9%9A%E4%BA%86%23","text":"今年过年没人催婚了","count":110749,"firstSeen":"2026-02-18T06:16:09.815Z","peakCount":110749,"prevCount":0,"velocity":100,"status":"new"},{"url":"/weibo?q=%23%E9%A9%AC%E5%87%A1%E8%88%92%E5%9B%9E%E5%BA%94%E6%98%A5%E6%99%9A%E5%8F%91%E5%9E%8B%E4%BA%89%E8%AE%AE%23","text":"马凡舒回应春晚发型争议","count":108800,"firstSeen":"2026-02-18T06:16:09.815Z","peakCount":108800,"prevCount":0,"velocity":100,"status":"new","textEn":"Ma Fanshu responds to Spring Festival Gala hairstyle controversy"},{"url":"/weibo?q=%23%E6%B4%97%E8%A1%A3%E6%9C%BA%E7%AB%9F%E7%94%A8%E9%94%99%E4%BA%86%E9%82%A3%E4%B9%88%E5%A4%9A%E5%B9%B4%23","text":"洗衣机竟用错了那么多年","count":104055,"firstSeen":"2026-02-18T06:16:09.815Z","peakCount":104055,"prevCount":0,"velocity":100,"status":"new"},{"url":"/weibo?q=%23%E6%83%8A%E8%9B%B0%E6%97%A0%E5%A3%B0%E8%B1%86%E7%93%A3%E5%BC%80%E5%88%866.3%23","text":"惊蛰无声豆瓣开分6.3","count":103343,"firstSeen":"2026-02-18T06:16:09.815Z","peakCount":103343,"prevCount":0,"velocity":100,"status":"new"},{"url":"/weibo?q=%23%E5%A7%90%E5%A6%B9%E4%BF%A9%E5%B9%B4%E5%B9%B4%E7%94%A8%E5%8E%8B%E5%B2%81%E9%92%B1%E4%B9%B0%E9%BB%84%E9%87%91%E6%94%92%E4%B8%8B80%E5%85%8B%23","text":"姐妹俩年年用压岁钱买黄金攒下80克","count":98391,"firstSeen":"2026-02-18T06:16:09.815Z","peakCount":98391,"prevCount":0,"velocity":100,"status":"new"},{"url":"/weibo?q=%23%E6%9C%88%E5%AB%82%E5%9B%9E%E5%BA%94%E4%B8%BA%E5%85%A5%E7%8B%B1%E9%9B%87%E4%B8%BB%E6%97%A0%E5%81%BF%E5%B8%A6%E5%A8%83%23","text":"月嫂回应为入狱雇主无偿带娃","count":94797,"firstSeen":"2026-02-18T06:16:09.815Z","peakCount":94797,"prevCount":0,"velocity":100,"status":"new"},{"url":"/weibo?q=%23%E5%88%98%E5%AE%87%E5%AE%81%E8%AF%B4%E5%A4%A7%E5%AE%B6%E8%BF%9B%E4%BA%86%E6%98%A5%E6%99%9A%E4%BC%91%E6%81%AF%E9%97%B4%E9%B8%A6%E9%9B%80%E6%97%A0%E5%A3%B0%23","text":"刘宇宁说大家进了春晚休息间鸦雀无声","count":91435,"firstSeen":"2026-02-18T06:16:09.815Z","peakCount":91435,"prevCount":0,"velocity":100,"status":"new"},{"url":"/weibo?q=%23%E7%89%B9%E6%96%AF%E6%8B%89%E5%AE%A3%E5%B8%83%E9%A6%96%E8%BE%86Cybercab%E4%B8%8B%E7%BA%BF%23","text":"特斯拉宣布首辆Cybercab下线","count":90924,"firstSeen":"2026-02-18T06:16:09.815Z","peakCount":90924,"prevCount":0,"velocity":100,"status":"new"},{"url":"/weibo?q=%23%E5%88%98%E6%97%B8%E7%94%A8%E5%8D%83%E9%97%AE%E7%82%B9%E4%B8%8A%E8%B1%86%E8%85%90%E5%A4%96%E5%8D%96%E4%BA%86%23","text":"刘旸用千问点上豆腐外卖了","count":76848,"firstSeen":"2026-02-18T06:16:09.815Z","peakCount":76848,"prevCount":0,"velocity":100,"status":"new"},{"url":"/weibo?q=%23%E4%B8%80%E5%AE%B617%E5%8F%A3%E8%BF%87%E5%B9%B4%E8%AF%B7%E7%A7%81%E5%8E%A8%E5%81%9A%E5%B9%B4%E5%A4%9C%E9%A5%AD%23","text":"一家17口过年请私厨做年夜饭","count":75346,"firstSeen":"2026-02-18T06:16:09.815Z","peakCount":75346,"prevCount":0,"velocity":100,"status":"new"},{"url":"/weibo?q=%23%E5%8D%97%E9%9D%9E%E5%8F%91%E7%8E%B080%E4%BA%BF%E5%85%89%E5%B9%B4%E5%A4%96%E5%AE%87%E5%AE%99%E7%81%AF%E5%A1%94%23","text":"南非发现80亿光年外宇宙灯塔","count":75116,"firstSeen":"2026-02-18T06:16:09.815Z","peakCount":75116,"prevCount":0,"velocity":100,"status":"new"},{"url":"/weibo?q=%23%E5%AD%A9%E5%AD%90%E5%AD%981000%E6%AF%94%E4%BD%A0%E5%AD%9820%E4%B8%87%E5%88%A9%E6%81%AF%E9%AB%98%23","text":"孩子存1000比你存20万利息高","count":74984,"firstSeen":"2026-02-18T06:16:09.815Z","peakCount":74984,"prevCount":0,"velocity":100,"status":"new","textEn":"If your child saves 1,000, the interest will be higher than if you save 200,000."},{"url":"/weibo?q=%23%E7%AC%AC%E4%B8%80%E6%AC%A1%E8%A7%81%E5%8F%A4%E8%A3%85%E5%89%A7%E7%94%B7%E4%B8%BB%E5%8F%AB%E5%A5%B3%E4%B8%BB%E7%B4%AB%E5%95%A7%23","text":"第一次见古装剧男主叫女主紫啧","count":65229,"firstSeen":"2026-02-18T06:16:09.815Z","peakCount":65229,"prevCount":0,"velocity":100,"status":"new"},{"url":"/weibo?q=%23%E6%8F%90%E5%89%8D%E4%B9%B0%E6%9C%BA%E7%A5%A8%E4%B8%80%E5%AE%B6%E5%9B%9B%E5%8F%A3%E8%A1%80%E4%BA%8F4000%23","text":"提前买机票一家四口血亏4000","count":60203,"firstSeen":"2026-02-18T06:16:09.815Z","peakCount":60203,"prevCount":0,"velocity":100,"status":"new"},{"url":"/weibo?q=%23%E5%A4%A7%E5%B9%B4%E5%88%9D%E4%BA%8C%E4%B8%8D%E5%8D%88%E7%9D%A1%23","text":"大年初二不午睡","count":1091928,"firstSeen":"2026-02-18T03:42:05.171Z","peakCount":1091928,"prevCount":770121,"velocity":42,"status":"rising"},{"url":"/weibo?q=%23%E9%A3%9E%E9%A9%B0%E4%BA%BA%E7%94%9F3%E7%A5%A8%E6%88%BF%E6%88%96%E8%B6%8550%E4%BA%BF%23","text":"飞驰人生3票房或超50亿","count":312811,"firstSeen":"2026-02-18T05:14:24.928Z","peakCount":312811,"prevCount":94384,"velocity":231,"status":"rising"},{"url":"/weibo?q=%23%E5%A5%B3%E7%94%9F%E5%8D%8A%E5%B9%B4%E5%8D%96%E5%87%BA800%E5%A4%9A%E5%8F%AA%E7%82%B9%E7%BF%A0%E5%A4%A7%E8%9F%91%E8%9E%82%23","text":"女生半年卖出800多只点翠大蟑螂","count":304842,"firstSeen":"2026-02-18T05:14:24.928Z","peakCount":304842,"prevCount":80473,"velocity":279,"status":"rising"},{"url":"/weibo?q=%23%E6%88%90%E4%BD%95%E4%BD%93%E7%BB%9F%E5%A4%A7%E7%BB%93%E5%B1%80%23","text":"成何体统大结局","count":259306,"firstSeen":"2026-02-18T05:14:24.928Z","peakCount":259306,"prevCount":205275,"velocity":26,"status":"rising"},{"url":"/weibo?q=%23%E6%9C%B1%E4%B8%80%E9%BE%99%E6%A2%A6%E7%94%B7%23","text":"朱一龙梦男","count":140505,"firstSeen":"2026-02-18T05:14:24.928Z","peakCount":140505,"prevCount":89390,"velocity":57,"status":"rising"},{"url":"/weibo?q=%23%E7%8C%AB%20%E4%BD%A0%E6%B2%A1%E6%9C%89%E8%87%AA%E5%B7%B1%E7%9A%84%E5%AE%B6%E5%90%97%23","text":"猫 你没有自己的家吗","count":140433,"firstSeen":"2026-02-18T05:14:24.928Z","peakCount":140433,"prevCount":69024,"velocity":103,"status":"rising"},{"url":"/weibo?q=%23%E8%8F%B2%E5%BE%8B%E5%AE%BE%E6%B5%B7%E8%AD%A6%E5%9C%A8%E5%8D%97%E6%B5%B7%E6%8A%95%E6%94%BE%E4%B8%8D%E6%98%8E%E7%89%A9%E4%BD%93%23","text":"菲律宾海警在南海投放不明物体","count":116726,"firstSeen":"2026-02-18T05:14:24.928Z","peakCount":116726,"prevCount":62471,"velocity":87,"status":"rising"},{"url":"/weibo?q=%23%E5%A8%9C%E7%84%B6%E4%B8%8E%E9%9C%8D%E5%AE%B6%E7%88%B6%E5%AD%90%E5%90%8C%E6%B8%B8%E6%84%8F%E5%A4%A7%E5%88%A9%23","text":"娜然与霍家父子同游意大利","count":114010,"textEn":"Naran traveled to Italy with the Huo family and his son","firstSeen":"2026-02-18T05:14:24.928Z","peakCount":114010,"prevCount":94546,"velocity":21,"status":"rising"},{"url":"/weibo?q=%23%E6%9D%8E%E5%85%B0%E8%BF%AA%20%E6%B2%A1%E6%9C%89%E9%A1%BA%E6%8B%90%23","text":"李兰迪 没有顺拐","count":106982,"firstSeen":"2026-02-18T05:14:24.928Z","peakCount":106982,"prevCount":68729,"velocity":56,"status":"rising"},{"url":"/weibo?q=%23%E7%8E%8B%E4%B8%80%E5%8D%9A%E6%98%93%E7%83%8A%E5%8D%83%E7%8E%BA%E6%98%A5%E6%99%9A%E7%A9%BF%E6%90%AD%E4%B8%8A%E6%A6%9C%E6%9C%80%E4%BD%B3%23","text":"王一博易烊千玺春晚穿搭上榜最佳","count":101051,"firstSeen":"2026-02-18T05:14:24.928Z","peakCount":101051,"prevCount":69153,"velocity":46,"status":"rising"},{"url":"/weibo?q=%23%E5%A4%A7%E4%BE%A6%E6%8E%A211%E5%BC%80%E6%92%AD%23","text":"大侦探11开播","count":94364,"firstSeen":"2026-02-18T05:14:24.928Z","peakCount":94364,"prevCount":87988,"velocity":7,"status":"hot"},{"url":"/weibo?q=%23%E6%88%90%E4%BD%95%E4%BD%93%E7%BB%9F%23","text":"成何体统","count":75075,"firstSeen":"2026-02-17T17:37:26.294Z","peakCount":113062,"prevCount":73008,"velocity":3,"status":"hot"},{"url":"/weibo?q=%23%E7%8C%AB%E5%92%AA%E7%AB%9F%E7%84%B6%E4%BC%9A%E6%8B%89%E8%A2%AB%E5%AD%90%23","text":"猫咪竟然会拉被子","count":70363,"firstSeen":"2026-02-18T05:14:24.928Z","peakCount":70363,"prevCount":68540,"velocity":3,"status":"hot"},{"url":"/weibo?q=%23%E4%B8%80%E9%83%A8%E7%9F%AD%E5%89%A7%E5%87%91%E9%BD%90%E4%B8%83%E4%B8%AA%E7%94%B7%E5%A6%B2%E5%B7%B1%23","text":"一部短剧凑齐七个男妲己","count":66853,"firstSeen":"2026-02-18T05:14:24.928Z","peakCount":76414,"prevCount":76414,"velocity":-13,"status":"hot"},{"url":"/weibo?q=%23%E8%B0%B7%E7%88%B1%E5%87%8C%20%E9%A1%B6%E7%BA%A7alpha%23","text":"谷爱凌 顶级alpha","count":140829,"firstSeen":"2026-02-18T03:42:05.171Z","peakCount":250074,"prevCount":182085,"velocity":-23,"status":"falling"},{"url":"/weibo?q=%23%E6%B2%88%E8%85%BE%E7%9C%8B%E4%BC%BC%E9%BC%93%E6%8E%8C%E5%AE%9E%E5%88%99%E6%89%94%E6%A9%98%E5%AD%90%E7%9A%AE%23","text":"沈腾看似鼓掌实则扔橘子皮","count":140774,"firstSeen":"2026-02-18T05:14:24.928Z","peakCount":586788,"prevCount":586788,"velocity":-76,"status":"falling"},{"url":"/weibo?q=%23%E9%AB%98%E5%B8%82%E6%97%A9%E8%8B%97%E5%86%85%E9%98%81%E9%9B%86%E4%BD%93%E8%BE%9E%E8%81%8C%23","text":"高市早苗内阁集体辞职","count":140729,"textEn":"Takaichi Sanae cabinet resigns en masse","firstSeen":"2026-02-18T00:57:45.051Z","peakCount":1123597,"prevCount":181819,"velocity":-23,"status":"falling"},{"url":"/weibo?q=%23%E5%88%98%E6%B5%A9%E5%AD%98%20%E4%BD%A0%E5%B0%B1%E6%98%AF%E6%9C%89%E5%A4%A9%E8%B5%8B%23","text":"刘浩存 你就是有天赋","count":140630,"firstSeen":"2026-02-18T05:14:24.928Z","peakCount":207462,"prevCount":207462,"velocity":-32,"status":"falling"},{"url":"/weibo?q=%23%E9%97%B2%E7%BD%AE1%E5%B9%B4%E7%9A%846%E7%B1%B3%E5%86%9C%E6%9D%91%E5%A4%A7%E7%82%95%E8%BF%87%E5%B9%B4%E7%9D%A1%E6%BB%A1%E4%BA%86%23","text":"闲置1年的6米农村大炕过年睡满了","count":140447,"textEn":"The 6-meter rural Kang that has been idle for a year is full of people sleeping during the Chinese New Year.","firstSeen":"2026-02-18T05:14:24.928Z","peakCount":213991,"prevCount":213991,"velocity":-34,"status":"falling"},{"url":"/weibo?q=%23%E8%BF%87%E5%B9%B4%E6%9C%9F%E9%97%B4%E7%9A%84%E8%83%83%23","text":"过年期间的胃","count":99628,"firstSeen":"2026-02-18T03:42:05.171Z","peakCount":194396,"prevCount":194396,"velocity":-49,"status":"falling"},{"url":"/weibo?q=%23%E9%95%96%E4%BA%BA%E5%8F%A3%E7%A2%91%23","text":"镖人口碑","count":96632,"firstSeen":"2026-02-18T03:42:05.171Z","peakCount":1074680,"prevCount":1074680,"velocity":-91,"status":"falling"},{"url":"/weibo?q=%23%E6%8B%89%E5%AE%8F%E6%A1%91%E6%98%A5%E6%99%9A%E5%90%8E%E5%8F%B0%E6%8E%A2%E7%8F%AD%20%E6%B2%A1%E6%9C%89%E4%B8%80%E7%A7%92%E4%B8%8D%E5%A5%BD%E7%AC%91%23","text":"拉宏桑春晚后台探班 没有一秒不好笑","count":90038,"firstSeen":"2026-02-18T03:42:05.171Z","peakCount":243728,"prevCount":178633,"velocity":-50,"status":"falling"},{"url":"/weibo?q=%23%E7%8E%8B%E6%A5%9A%E7%84%B6%E5%87%BA%E5%9C%88%E9%95%9C%E5%A4%B4%23","text":"王楚然出圈镜头","count":89947,"firstSeen":"2026-02-18T03:42:05.171Z","peakCount":218901,"prevCount":167439,"velocity":-46,"status":"falling"},{"url":"/weibo?q=%23i%E4%BA%BA%E7%9A%84%E8%BF%87%E5%B9%B4%E7%8E%B0%E7%8A%B6%23","text":"i人的过年现状","count":88949,"firstSeen":"2026-02-18T05:14:24.928Z","peakCount":189645,"prevCount":189645,"velocity":-53,"status":"falling"},{"url":"/weibo?q=%23%E9%A3%9E%E9%A9%B0%E4%BA%BA%E7%94%9F3%20%E7%88%BD%E7%89%87%23","text":"飞驰人生3 爽片","count":76426,"firstSeen":"2026-02-18T05:14:24.928Z","peakCount":117591,"prevCount":117591,"velocity":-35,"status":"falling"},{"url":"/weibo?q=%23%E4%B8%9E%E7%A3%8A%E7%9C%9F%E7%9A%84%E8%AF%BB%E4%BA%86%E4%B8%8E%E5%A6%BB%E4%B9%A6%23","text":"丞磊真的读了与妻书","count":75195,"textEn":"Cheng Lei really read the book with his wife","firstSeen":"2026-02-18T03:42:05.171Z","peakCount":563559,"prevCount":172485,"velocity":-56,"status":"falling"},{"url":"/weibo?q=%23%E5%A5%B3%E5%AD%90%E6%A5%BC%E9%81%93%E6%99%BE%E6%99%9216%E6%96%A4%E5%92%B8%E8%82%89%E6%92%92%E6%89%8B%E6%B2%A1%23","text":"女子楼道晾晒16斤咸肉撒手没","count":70507,"firstSeen":"2026-02-18T03:42:05.171Z","peakCount":149294,"prevCount":93446,"velocity":-25,"status":"falling"},{"url":"/weibo?q=%23%E6%97%A5%E6%9C%AC%E8%A6%81%E5%BD%93%E5%86%A4%E5%A4%A7%E5%A4%B4%E4%BA%86%23","text":"日本要当冤大头了","count":1150521,"firstSeen":"2026-02-18T03:42:05.171Z","peakCount":1150521,"prevCount":1150521,"velocity":-100,"status":"gone","textEn":"Japan is going to be taken advantage of"},{"url":"/weibo?q=%23%E5%80%BC%E5%BE%97%E4%B8%80%E5%88%B7%E5%86%8D%E5%88%B7%E7%9A%84%E6%98%A5%E6%99%9A%E7%9E%AC%E9%97%B4%23","text":"值得一刷再刷的春晚瞬间","count":641988,"firstSeen":"2026-02-18T03:42:05.171Z","peakCount":641988,"prevCount":641988,"velocity":-100,"status":"gone"},{"url":"/weibo?q=%23%E5%AE%8B%E5%B0%8F%E5%AE%9D%20%E5%B0%8F%E5%93%81%E7%BF%BB%E8%BD%A6%23","text":"宋小宝 小品翻车","count":634024,"textEn":"Song Xiaobao skit overturned","firstSeen":"2026-02-17T17:37:26.294Z","peakCount":634024,"prevCount":634024,"velocity":-100,"status":"gone"},{"url":"/weibo?q=%232026%E6%98%A5%E8%8A%82%E6%B6%88%E8%B4%B9%E8%BF%8E%E6%9D%A5%E5%BC%80%E9%97%A8%E7%BA%A2%23","text":"2026春节消费迎来开门红","count":624994,"firstSeen":"2026-02-18T05:14:24.928Z","peakCount":624994,"prevCount":624994,"velocity":-100,"status":"gone","textEn":"2026 Spring Festival consumption gets off to a good start"},{"url":"/weibo?q=%23%E7%9C%8B%E4%BA%86%E6%98%A5%E6%99%9A%E6%83%B3%E8%B5%B4%E7%9A%96%23","text":"看了春晚想赴皖","count":616971,"firstSeen":"2026-02-18T05:14:24.928Z","peakCount":616971,"prevCount":616971,"velocity":-100,"status":"gone"},{"url":"/weibo?q=%23%E6%98%A5%E8%8A%82AI%E7%BE%8E%E9%A3%9F%23","text":"春节AI美食","count":581598,"firstSeen":"2026-02-18T03:42:05.171Z","peakCount":581598,"prevCount":581598,"velocity":-100,"status":"gone","textEn":"Spring Festival AI Food"},{"url":"/weibo?q=%23%E5%A5%A5%E8%BF%AA%E6%8A%BD%E5%A5%96%E9%80%81%E8%BD%A6%E9%99%A4%E5%A4%95%E7%A6%8F%E5%88%A9%E8%BF%94%E5%9C%BA%23","text":"奥迪抽奖送车除夕福利返场","count":250374,"firstSeen":"2026-02-17T22:44:04.394Z","peakCount":250374,"prevCount":250374,"velocity":-100,"status":"gone","textEn":"Audi returns with lucky draw and car giveaway on New Year’s Eve"},{"url":"/weibo?q=%23%E7%9C%8B%E7%86%8A%E5%87%BA%E6%B2%A1%E5%AD%A9%E5%AD%90%E5%BC%80%E5%BF%83%E5%AE%B6%E9%95%BF%E6%94%BE%E5%BF%83%23","text":"看熊出没孩子开心家长放心","count":248034,"textEn":"Watching bears come and go, children are happy, parents are reassured","firstSeen":"2026-02-17T20:03:39.544Z","peakCount":248034,"prevCount":248034,"velocity":-100,"status":"gone"},{"url":"/weibo?q=%232026%E6%96%B0%E6%98%A5%E8%B5%B0%E5%9F%BA%E5%B1%82%23","text":"2026新春走基层","count":246967,"firstSeen":"2026-02-17T17:37:26.294Z","peakCount":650467,"prevCount":246967,"velocity":-100,"status":"gone","textEn":"2026 New Year Goes to the Grassroots"},{"url":"/weibo?q=%23%E4%B8%80%E8%B5%B7%E5%90%83%E9%A1%BF%E5%B9%B4%E5%A4%9C%E9%A5%AD%23","text":"一起吃顿年夜饭","count":230784,"firstSeen":"2026-02-18T00:57:45.051Z","peakCount":230784,"prevCount":230784,"velocity":-100,"status":"gone"},{"url":"/weibo?q=%23%E7%BD%91%E6%B0%91%E9%80%A0%E8%B0%A3%E9%9D%9E%E6%B4%B2%E7%8C%AA%E7%98%9F%E5%9C%A8%E6%9C%AC%E5%9C%B0%E4%BC%A0%E6%92%AD%E8%A2%AB%E7%BD%9A%23","text":"网民造谣非洲猪瘟在本地传播被罚","count":207288,"firstSeen":"2026-02-18T05:14:24.928Z","peakCount":207288,"prevCount":207288,"velocity":-100,"status":"gone"},{"url":"/weibo?q=%23%E5%8D%83%E9%97%AE%E8%AE%A9%E6%95%A3%E8%A3%85%E8%8B%8F%E8%B6%85%E5%85%B7%E8%B1%A1%E5%8C%96%E4%BA%86%23","text":"千问让散装苏超具象化了","count":185246,"firstSeen":"2026-02-18T03:42:05.171Z","peakCount":185246,"prevCount":185246,"velocity":-100,"status":"gone"},{"url":"/weibo?q=%23%E6%B2%88%E8%85%BE%E5%9D%A6%E8%A8%80%E5%9B%A0%E6%98%A5%E6%99%9A%E8%AF%B4%E9%94%99%E8%AF%8D%E5%8D%81%E5%88%86%E8%87%AA%E8%B4%A3%23","text":"沈腾坦言因春晚说错词十分自责","count":180615,"firstSeen":"2026-02-17T23:47:12.011Z","peakCount":180615,"prevCount":180615,"velocity":-100,"status":"gone"},{"url":"/weibo?q=%23%E5%A4%A7%E5%B9%B4%E5%88%9D%E4%BA%8C%E4%B8%8D%E8%83%BD%E5%81%9A%E5%93%AA%E4%BA%9B%E4%BA%8B%23","text":"大年初二不能做哪些事","count":177931,"firstSeen":"2026-02-18T03:42:05.171Z","peakCount":248653,"prevCount":177931,"velocity":-100,"status":"gone"},{"url":"/weibo?q=%23%E6%9C%89%E6%B8%B8%E5%AE%A2%E5%A4%A7%E5%B9%B4%E5%88%9D%E4%B8%80%E6%8D%A1%E6%BC%8F%E6%9C%BA%E7%A5%A8%E5%87%BA%E6%B8%B8%23","text":"有游客大年初一捡漏机票出游","count":169381,"firstSeen":"2026-02-18T03:42:05.171Z","peakCount":169381,"prevCount":169381,"velocity":-100,"status":"gone"},{"url":"/weibo?q=%23%E5%88%98%E8%AF%97%E8%AF%97%20%E7%BE%8E%E4%BA%BA%E8%90%BD%E6%B3%AA%23","text":"刘诗诗 美人落泪","count":169291,"firstSeen":"2026-02-18T03:42:05.171Z","peakCount":169291,"prevCount":169291,"velocity":-100,"status":"gone"},{"url":"/weibo?q=%23%E8%B0%88%E6%81%8B%E7%88%B1%E8%A6%81%E8%B7%9F%E6%9C%89%E5%B0%91%E5%B9%B4%E6%B0%94%E7%9A%84%E4%BA%BA%E8%B0%88%23","text":"谈恋爱要跟有少年气的人谈","count":166015,"firstSeen":"2026-02-18T03:42:05.171Z","peakCount":166015,"prevCount":166015,"velocity":-100,"status":"gone"},{"url":"/weibo?q=%23%E7%86%8A%E7%8C%AB%E8%AE%A1%E5%88%92%E5%85%A8%E5%AE%B6%E5%BF%AB%E4%B9%90%E5%BC%80%E5%85%B3%23","text":"熊猫计划全家快乐开关","count":156769,"firstSeen":"2026-02-17T23:47:12.011Z","peakCount":156769,"prevCount":156769,"velocity":-100,"status":"gone"},{"url":"/weibo?q=%23%E5%A5%B3%E5%AD%90%E5%9B%9E%E5%BA%94%E5%9B%9E%E5%A8%98%E5%AE%B6%E5%8F%AA%E9%9C%801%E7%A7%92%E9%92%9F%23","text":"女子回应回娘家只需1秒钟","count":120212,"firstSeen":"2026-02-18T05:14:24.928Z","peakCount":120212,"prevCount":120212,"velocity":-100,"status":"gone","textEn":"It only takes 1 second for the woman to respond that she will go back to her parents’ home."},{"url":"/weibo?q=%23%E5%B0%8F%E5%AD%A9%E5%93%A5%E7%A7%B0%E5%9C%A8%E5%B0%8F%E5%8C%BA%E6%90%9E%E4%BA%862%E5%8D%83%E5%A4%9A%E7%BA%A2%E5%8C%85%23","text":"小孩哥称在小区搞了2千多红包","count":119189,"firstSeen":"2026-02-18T03:42:05.171Z","peakCount":119189,"prevCount":119189,"velocity":-100,"status":"gone"},{"url":"/weibo?q=%23%E5%88%9D%E4%BA%8C%E5%92%8C%E5%88%9D%E4%BA%94%E7%9A%84%E8%B4%A2%E7%A5%9E%E4%B8%80%E6%A0%B7%E5%90%97%23","text":"初二和初五的财神一样吗","count":117713,"firstSeen":"2026-02-17T17:37:26.294Z","peakCount":117713,"prevCount":117713,"velocity":-100,"status":"gone"},{"url":"/weibo?q=%23%E6%9D%8E%E7%90%B0%E6%95%99%E7%BB%83%E5%BA%86%E7%A5%9D%E4%B8%AD%E5%9B%BD%E9%98%9F%E9%93%9C%E7%89%8C%23","text":"李琰教练庆祝中国队铜牌","count":114842,"textEn":"Coach Li Yan celebrates the bronze medal of the Chinese team","firstSeen":"2026-02-17T23:14:31.984Z","peakCount":114842,"prevCount":114842,"velocity":-100,"status":"gone"},{"url":"/weibo?q=%23%E7%8E%8B%E8%8F%B2%E5%8C%96%E5%A6%86%E5%B8%88%E6%94%B9%E5%8F%A3%E9%97%AE%E5%B0%B1%E6%98%AFAI%23","text":"王菲化妆师改口问就是AI","count":114029,"textEn":"Faye Wong’s makeup artist changed her mind and asked that it was AI","firstSeen":"2026-02-17T17:37:26.294Z","peakCount":114029,"prevCount":114029,"velocity":-100,"status":"gone"},{"url":"/weibo?q=%23%E4%BB%8A%E5%B9%B4%E6%89%80%E6%9C%89%E6%B3%95%E5%AE%9A%E5%81%87%E6%97%A5%E5%85%A8%E4%B8%8E%E5%91%A8%E6%9C%AB%E9%87%8D%E5%90%88%23","text":"今年所有法定假日全与周末重合","count":111928,"textEn":"All statutory holidays this year coincide with weekends","firstSeen":"2026-02-17T17:37:26.294Z","peakCount":111928,"prevCount":111928,"velocity":-100,"status":"gone"},{"url":"/weibo?q=%23%E5%AE%8B%E5%B0%8F%E5%AE%9D%E7%8E%B0%E6%8C%82%23","text":"宋小宝现挂","count":110761,"firstSeen":"2026-02-17T23:47:12.011Z","peakCount":110761,"prevCount":110761,"velocity":-100,"status":"gone","textEn":"Song Xiaobao is now available"},{"url":"/weibo?q=%23%E6%98%A5%E6%99%9A%E6%80%BB%E5%AF%BC%E6%BC%94%E8%AF%B4%E8%B4%BA%E8%8A%B1%E7%A5%9E%E9%9D%9E%E5%B8%B8%E9%9D%9E%E5%B8%B8%E9%9A%BE%23","text":"春晚总导演说贺花神非常非常难","count":109453,"firstSeen":"2026-02-18T00:57:45.051Z","peakCount":109453,"prevCount":109453,"velocity":-100,"status":"gone"},{"url":"/weibo?q=%23%E5%85%A8%E5%9B%BD%E5%88%9D%E4%BA%8C%E5%9B%9E%E5%A8%98%E5%AE%B6%E7%9A%84%E5%A5%B3%E5%A9%BFbelike%23","text":"全国初二回娘家的女婿belike","count":107434,"textEn":"The son-in-law who returned to his parents' home in the second grade of junior high school across the country belike","firstSeen":"2026-02-17T17:37:26.294Z","peakCount":107434,"prevCount":107434,"velocity":-100,"status":"gone"},{"url":"/weibo?q=%23%E5%88%98%E5%B0%91%E6%98%82%E6%9E%97%E5%AD%9D%E5%9F%88%E6%90%BA%E6%89%8B%E5%87%BA%E6%88%98%23","text":"刘少昂林孝埈携手出战","count":102481,"textEn":"Liu Shaoang and Lin Xiaoqi join hands to fight","firstSeen":"2026-02-18T03:42:05.171Z","peakCount":241030,"prevCount":102481,"velocity":-100,"status":"gone"},{"url":"/weibo?q=%23%E5%86%AC%E5%A5%A5%E4%BC%9A%E9%9C%B2%E5%86%85%E8%A1%A3%E5%93%81%E7%89%8C%E5%A5%B3%E9%80%89%E6%89%8B%E5%BC%95%E6%9D%A5%E5%B9%BF%E5%91%8A%E5%95%86%23","text":"冬奥会露内衣品牌女选手引来广告商","count":100834,"textEn":"Brand of female athletes exposing underwear at Winter Olympics attracts advertisers","firstSeen":"2026-02-17T17:37:26.294Z","peakCount":100834,"prevCount":100834,"velocity":-100,"status":"gone"},{"url":"/weibo?q=%23%E8%B0%B7%E7%88%B1%E5%87%8C%E8%AF%B4%E7%97%9B%E5%A4%B12%E5%9D%97%E9%87%91%E7%89%8C%E8%AF%B4%E6%B3%95%E5%A4%AA%E8%8D%92%E8%B0%AC%23","text":"谷爱凌说痛失2块金牌说法太荒谬","count":98815,"firstSeen":"2026-02-17T23:47:12.011Z","peakCount":224561,"prevCount":98815,"velocity":-100,"status":"gone"},{"url":"/weibo?q=%23%E5%9B%9E%E8%80%81%E5%AE%B6%E5%90%8E%E6%A0%B9%E6%9C%AC%E6%B2%A1%E6%9C%89%E7%A9%BF%E8%A1%A3%E7%84%A6%E8%99%91%23","text":"回老家后根本没有穿衣焦虑","count":98396,"firstSeen":"2026-02-18T03:42:05.171Z","peakCount":244410,"prevCount":98396,"velocity":-100,"status":"gone"},{"url":"/weibo?q=%23%E7%8E%8B%E6%A5%9A%E7%84%B6%E7%BE%8E%E5%88%B0%E6%88%90%E4%BD%95%E4%BD%93%E7%BB%9F%23","text":"王楚然美到成何体统","count":96079,"firstSeen":"2026-02-18T03:42:05.171Z","peakCount":96079,"prevCount":96079,"velocity":-100,"status":"gone","textEn":"How beautiful is Wang Churan?"},{"url":"/weibo?q=%23%E4%BD%93%E8%82%B2AI%E8%BF%87%E5%A4%A7%E5%B9%B4%23","text":"体育AI过大年","count":95637,"firstSeen":"2026-02-18T05:14:24.928Z","peakCount":95637,"prevCount":95637,"velocity":-100,"status":"gone","textEn":"Sports AI celebrates Chinese New Year"},{"url":"/weibo?q=%23%E9%95%96%E4%BA%BA%E7%8E%89%E9%9D%A2%E9%AC%BC%23","text":"镖人玉面鬼","count":94936,"firstSeen":"2026-02-18T03:42:05.171Z","peakCount":94936,"prevCount":94936,"velocity":-100,"status":"gone"},{"url":"/weibo?q=%23%E5%A4%A7%E5%B9%B4%E5%88%9D%E4%BA%8C%23","text":"大年初二","count":93953,"firstSeen":"2026-02-18T00:57:45.051Z","peakCount":93953,"prevCount":93953,"velocity":-100,"status":"gone","textEn":"The second day of the Lunar New Year"},{"url":"/weibo?q=%23%E6%98%A5%E6%99%9A%E7%9C%8B%E8%BF%AA%E4%B8%BD%E7%83%AD%E5%B7%B4%E7%9C%8B%E5%85%A5%E8%BF%B7%E4%BA%86%23","text":"春晚看迪丽热巴看入迷了","count":93152,"firstSeen":"2026-02-18T03:42:05.171Z","peakCount":93152,"prevCount":93152,"velocity":-100,"status":"gone"},{"url":"/weibo?q=%23%E6%9D%8E%E5%AD%90%E6%9F%92%E5%9C%A8%E6%98%A5%E6%99%9A%E5%90%8E%E5%8F%B0%E6%89%8B%E6%90%93%E9%9D%9E%E9%81%97%E9%A5%B0%E5%93%81%23","text":"李子柒在春晚后台手搓非遗饰品","count":92888,"firstSeen":"2026-02-17T23:47:12.011Z","peakCount":272423,"prevCount":92888,"velocity":-100,"status":"gone"},{"url":"/weibo?q=%23%E4%B8%AD%E5%9B%BD%E9%80%9F%E6%BB%91%E7%94%B7%E5%9B%A2%E9%93%9C%E7%89%8C%23","text":"中国速滑男团铜牌","count":86051,"firstSeen":"2026-02-17T17:37:26.294Z","peakCount":698376,"prevCount":86051,"velocity":-100,"status":"gone"},{"url":"/weibo?q=%23%E5%85%A8%E5%AE%B6%E5%BF%98%E5%B8%A6%E9%92%A5%E5%8C%99%E5%B0%8F%E7%8C%AB%E7%94%A85%E5%88%86%E9%92%9F%E5%BC%80%E9%97%A8%23","text":"全家忘带钥匙小猫用5分钟开门","count":83632,"firstSeen":"2026-02-18T03:42:05.171Z","peakCount":83632,"prevCount":83632,"velocity":-100,"status":"gone","textEn":"The whole family forgot their keys and the cat took 5 minutes to open the door."},{"url":"/weibo?q=%23%E5%88%98%E4%B8%89%E7%9E%B3%E5%9B%9E%E5%BA%94%E6%8A%84%E8%A2%AD%23","text":"刘三瞳回应抄袭","count":83001,"firstSeen":"2026-02-18T03:42:05.171Z","peakCount":83001,"prevCount":83001,"velocity":-100,"status":"gone"},{"url":"/weibo?q=%23%E5%B1%B1%E4%B8%9C%E4%B8%80%E6%9D%91600%E5%A4%9A%E4%BA%BA%E9%9B%86%E4%BD%93%E7%A3%95%E5%A4%B4%E6%8B%9C%E5%B9%B4%23","text":"山东一村600多人集体磕头拜年","count":82289,"firstSeen":"2026-02-17T19:32:46.495Z","peakCount":82289,"prevCount":82289,"velocity":-100,"status":"gone"},{"url":"/weibo?q=%23%E9%A9%AC%E9%A0%94%E5%8F%91%E8%A7%86%E9%A2%91%E7%82%AB%E8%80%80%E6%9D%8E%E7%BA%AF%E7%99%BB%E4%B8%8A%E5%A4%AE%E8%A7%86%E6%98%A5%E6%99%9A%23","text":"马頔发视频炫耀李纯登上央视春晚","count":82194,"firstSeen":"2026-02-17T23:47:12.011Z","peakCount":82194,"prevCount":82194,"velocity":-100,"status":"gone","textEn":"Ma Di posted a video showing off Li Chun’s appearance on CCTV Spring Festival Gala"},{"url":"/weibo?q=%23%E6%AD%A3%E7%A1%AE%E8%B5%B0%E8%B7%AF%E5%A7%BF%E5%8A%BF%E6%98%AF%E7%94%A8%E8%87%80%E8%80%8C%E4%B8%8D%E6%98%AF%E8%85%BF%23","text":"正确走路姿势是用臀而不是腿","count":82153,"textEn":"Correct walking posture is to use your hips, not your legs","firstSeen":"2026-02-17T17:37:26.294Z","peakCount":82153,"prevCount":82153,"velocity":-100,"status":"gone"},{"url":"/weibo?q=%23%E4%B8%89%E6%96%87%E9%B1%BC%E5%85%B6%E5%AE%9E%E6%98%AF%E6%B5%B7%E5%BA%95%E5%A4%A7%E8%82%A5%E7%8C%AA%23","text":"三文鱼其实是海底大肥猪","count":82142,"textEn":"Salmon is actually a big fat pig on the bottom of the sea","firstSeen":"2026-02-17T17:37:26.294Z","peakCount":82142,"prevCount":82142,"velocity":-100,"status":"gone"},{"url":"/weibo?q=%23B%E7%AB%99%E8%AF%AD%E8%A8%80%E7%B1%BB%E8%8A%82%E7%9B%AE%20%E8%B5%A2%E9%BA%BB%E4%BA%86%23","text":"B站语言类节目 赢麻了","count":82116,"textEn":"The language program at Station B is a winner","firstSeen":"2026-02-17T17:37:26.294Z","peakCount":121865,"prevCount":82116,"velocity":-100,"status":"gone"},{"url":"/weibo?q=%23%E7%88%B6%E4%BA%B2%E5%8E%BB%E4%B8%96%E6%91%86%E6%91%8A%E5%8D%96%E5%AF%B9%E8%81%94%E7%94%B7%E5%AD%A9%E6%AF%8D%E4%BA%B2%E5%8F%91%E5%A3%B0%23","text":"父亲去世摆摊卖对联男孩母亲发声","count":81615,"textEn":"The mother of a boy selling couplets at a stall after his father passed away speaks out","firstSeen":"2026-02-18T00:57:45.051Z","peakCount":82239,"prevCount":81615,"velocity":-100,"status":"gone"},{"url":"/weibo?q=%23%E5%A4%AE%E8%A7%86%E6%98%A5%E6%99%9A%E7%9B%B4%E6%92%AD%E6%80%BB%E6%94%B6%E8%A7%86%E4%BB%BD%E9%A2%9D%E5%88%9B13%E5%B9%B4%E6%9D%A5%E6%96%B0%E9%AB%98%23","text":"央视春晚直播总收视份额创13年来新高","count":81409,"firstSeen":"2026-02-18T03:42:05.171Z","peakCount":81409,"prevCount":81409,"velocity":-100,"status":"gone"},{"url":"/weibo?q=%23%E9%A3%9E%E9%A9%B0%E4%BA%BA%E7%94%9F3%E6%88%90%E5%A4%A7%E5%B9%B4%E5%88%9D%E4%B8%80%E7%A5%A8%E6%88%BF%E5%86%A0%E5%86%9B%23","text":"飞驰人生3成大年初一票房冠军","count":81230,"firstSeen":"2026-02-18T03:42:05.171Z","peakCount":81230,"prevCount":81230,"velocity":-100,"status":"gone"},{"url":"/weibo?q=%23%E8%93%9D%E7%9B%88%E8%8E%B9%E5%A4%AE%E8%A7%86%E5%B9%B4%E5%BA%A6%E8%A7%82%E4%BC%97%E5%96%9C%E7%88%B1%E6%BC%94%E5%91%98%23","text":"蓝盈莹央视年度观众喜爱演员","count":81173,"firstSeen":"2026-02-18T00:57:45.051Z","peakCount":81173,"prevCount":81173,"velocity":-100,"status":"gone"},{"url":"/weibo?q=%23%E5%B0%8F%E9%85%92%E7%AA%9D%E5%81%9A%E7%AE%A1%E4%B9%90%E7%9A%84%E8%8A%B1%E7%AB%A5%E4%BA%86%23","text":"小酒窝做管乐的花童了","count":80614,"firstSeen":"2026-02-17T23:47:12.011Z","peakCount":80614,"prevCount":80614,"velocity":-100,"status":"gone"}]